{"search-results": {"opensearch:totalResults": "43", "opensearch:startIndex": "0", "opensearch:itemsPerPage": "43", "opensearch:Query": {"@role": "request", "@searchTerms": "issn(0960085X)", "@startPage": "0"}, "link": [{"@_fa": "true", "@ref": "self", "@href": "https://api.elsevier.com/content/search/scopus?start=0&count=200&query=issn%280960085X%29&date=2013&apiKey=ad4e12568b69167a2d25213b52923901&insttoken=0363e8707601cf3e7f27138d2b25f9e4&view=STANDARD", "@type": "application/json"}, {"@_fa": "true", "@ref": "first", "@href": "https://api.elsevier.com/content/search/scopus?start=0&count=200&query=issn%280960085X%29&date=2013&apiKey=ad4e12568b69167a2d25213b52923901&insttoken=0363e8707601cf3e7f27138d2b25f9e4&view=STANDARD", "@type": "application/json"}], "entry": [{"@_fa": "true", "link": [{"@_fa": "true", "@ref": "self", "@href": "https://api.elsevier.com/content/abstract/scopus_id/84887123965"}, {"@_fa": "true", "@ref": "author-affiliation", "@href": "https://api.elsevier.com/content/abstract/scopus_id/84887123965?field=author,affiliation"}, {"@_fa": "true", "@ref": "scopus", "@href": "https://www.scopus.com/inward/record.uri?partnerID=HzOxMe3b&scp=84887123965&origin=inward"}, {"@_fa": "true", "@ref": "scopus-citedby", "@href": "https://www.scopus.com/inward/citedby.uri?partnerID=HzOxMe3b&scp=84887123965&origin=inward"}], "prism:url": "https://api.elsevier.com/content/abstract/scopus_id/84887123965", "dc:identifier": "SCOPUS_ID:84887123965", "eid": "2-s2.0-84887123965", "dc:title": "Does risk matter? Disengagement from risk management practices in information systems projects", "dc:creator": "Kutsch E.", "prism:publicationName": "European Journal of Information Systems", "prism:issn": "0960085X", "prism:eIssn": "14769344", "prism:volume": "22", "prism:issueIdentifier": "6", "prism:pageRange": "637-649", "prism:coverDate": "2013-01-01", "prism:coverDisplayDate": "November 2013", "prism:doi": "10.1057/ejis.2012.6", "pii": "EJIS20126", "citedby-count": "28", "affiliation": [{"@_fa": "true", "affilname": "Cranfield School of Management", "affiliation-city": "Cranfield", "affiliation-country": "United Kingdom"}], "prism:aggregationType": "Journal", "subtype": "ar", "subtypeDescription": "Article", "source-id": "15074", "openaccess": "0", "openaccessFlag": false}, {"@_fa": "true", "link": [{"@_fa": "true", "@ref": "self", "@href": "https://api.elsevier.com/content/abstract/scopus_id/84887119253"}, {"@_fa": "true", "@ref": "author-affiliation", "@href": "https://api.elsevier.com/content/abstract/scopus_id/84887119253?field=author,affiliation"}, {"@_fa": "true", "@ref": "scopus", "@href": "https://www.scopus.com/inward/record.uri?partnerID=HzOxMe3b&scp=84887119253&origin=inward"}, {"@_fa": "true", "@ref": "scopus-citedby", "@href": "https://www.scopus.com/inward/citedby.uri?partnerID=HzOxMe3b&scp=84887119253&origin=inward"}], "prism:url": "https://api.elsevier.com/content/abstract/scopus_id/84887119253", "dc:identifier": "SCOPUS_ID:84887119253", "eid": "2-s2.0-84887119253", "dc:title": "Journals and conferences in discourse", "dc:creator": "Te'eni D.", "prism:publicationName": "European Journal of Information Systems", "prism:issn": "0960085X", "prism:eIssn": "14769344", "prism:volume": "22", "prism:issueIdentifier": "6", "prism:pageRange": "589-591", "prism:coverDate": "2013-01-01", "prism:coverDisplayDate": "November 2013", "prism:doi": "10.1057/ejis.2013.30", "pii": "EJIS201330", "citedby-count": "5", "prism:aggregationType": "Journal", "subtype": "ed", "subtypeDescription": "Editorial", "source-id": "15074", "openaccess": "0", "openaccessFlag": false}, {"@_fa": "true", "link": [{"@_fa": "true", "@ref": "self", "@href": "https://api.elsevier.com/content/abstract/scopus_id/84887105855"}, {"@_fa": "true", "@ref": "author-affiliation", "@href": "https://api.elsevier.com/content/abstract/scopus_id/84887105855?field=author,affiliation"}, {"@_fa": "true", "@ref": "scopus", "@href": "https://www.scopus.com/inward/record.uri?partnerID=HzOxMe3b&scp=84887105855&origin=inward"}, {"@_fa": "true", "@ref": "scopus-citedby", "@href": "https://www.scopus.com/inward/citedby.uri?partnerID=HzOxMe3b&scp=84887105855&origin=inward"}], "prism:url": "https://api.elsevier.com/content/abstract/scopus_id/84887105855", "dc:identifier": "SCOPUS_ID:84887105855", "eid": "2-s2.0-84887105855", "dc:title": "Empirical investigation of the usefulness of gateway constructs in process models", "dc:creator": "Recker J.", "prism:publicationName": "European Journal of Information Systems", "prism:issn": "0960085X", "prism:eIssn": "14769344", "prism:volume": "22", "prism:issueIdentifier": "6", "prism:pageRange": "673-689", "prism:coverDate": "2013-01-01", "prism:coverDisplayDate": "November 2013", "prism:doi": "10.1057/ejis.2012.50", "pii": "EJIS201250", "citedby-count": "36", "affiliation": [{"@_fa": "true", "affilname": "Queensland University of Technology", "affiliation-city": "Brisbane", "affiliation-country": "Australia"}], "prism:aggregationType": "Journal", "subtype": "ar", "subtypeDescription": "Article", "source-id": "15074", "openaccess": "0", "openaccessFlag": false, "freetoread": {"value": [{"$": "all"}, {"$": "repository"}, {"$": "repositoryvor"}]}, "freetoreadLabel": {"value": [{"$": "All Open Access"}, {"$": "Green"}]}}, {"@_fa": "true", "link": [{"@_fa": "true", "@ref": "self", "@href": "https://api.elsevier.com/content/abstract/scopus_id/84887086166"}, {"@_fa": "true", "@ref": "author-affiliation", "@href": "https://api.elsevier.com/content/abstract/scopus_id/84887086166?field=author,affiliation"}, {"@_fa": "true", "@ref": "scopus", "@href": "https://www.scopus.com/inward/record.uri?partnerID=HzOxMe3b&scp=84887086166&origin=inward"}, {"@_fa": "true", "@ref": "scopus-citedby", "@href": "https://www.scopus.com/inward/citedby.uri?partnerID=HzOxMe3b&scp=84887086166&origin=inward"}], "prism:url": "https://api.elsevier.com/content/abstract/scopus_id/84887086166", "dc:identifier": "SCOPUS_ID:84887086166", "eid": "2-s2.0-84887086166", "dc:title": "IS integration and knowledge sharing in multi-unit firms: The winner's curse \u2020", "dc:creator": "Saraf N.", "prism:publicationName": "European Journal of Information Systems", "prism:issn": "0960085X", "prism:eIssn": "14769344", "prism:volume": "22", "prism:issueIdentifier": "6", "prism:pageRange": "592-603", "prism:coverDate": "2013-01-01", "prism:coverDisplayDate": "November 2013", "prism:doi": "10.1057/ejis.2012.37", "pii": "EJIS201237", "citedby-count": "16", "affiliation": [{"@_fa": "true", "affilname": "Beedie School of Business", "affiliation-city": "Burnaby", "affiliation-country": "Canada"}], "prism:aggregationType": "Journal", "subtype": "ar", "subtypeDescription": "Article", "source-id": "15074", "openaccess": "0", "openaccessFlag": false}, {"@_fa": "true", "link": [{"@_fa": "true", "@ref": "self", "@href": "https://api.elsevier.com/content/abstract/scopus_id/84887084623"}, {"@_fa": "true", "@ref": "author-affiliation", "@href": "https://api.elsevier.com/content/abstract/scopus_id/84887084623?field=author,affiliation"}, {"@_fa": "true", "@ref": "scopus", "@href": "https://www.scopus.com/inward/record.uri?partnerID=HzOxMe3b&scp=84887084623&origin=inward"}, {"@_fa": "true", "@ref": "scopus-citedby", "@href": "https://www.scopus.com/inward/citedby.uri?partnerID=HzOxMe3b&scp=84887084623&origin=inward"}], "prism:url": "https://api.elsevier.com/content/abstract/scopus_id/84887084623", "dc:identifier": "SCOPUS_ID:84887084623", "eid": "2-s2.0-84887084623", "dc:title": "Why the first provider takes it all: The consequences of a low trust culture on pricing and ratings in online sourcing markets", "dc:creator": "Gefen D.", "prism:publicationName": "European Journal of Information Systems", "prism:issn": "0960085X", "prism:eIssn": "14769344", "prism:volume": "22", "prism:issueIdentifier": "6", "prism:pageRange": "604-618", "prism:coverDate": "2013-01-01", "prism:coverDisplayDate": "November 2013", "prism:doi": "10.1057/ejis.2012.49", "pii": "EJIS201249", "citedby-count": "12", "affiliation": [{"@_fa": "true", "affilname": "LeBow College of Business", "affiliation-city": "Philadelphia", "affiliation-country": "United States"}], "prism:aggregationType": "Journal", "subtype": "ar", "subtypeDescription": "Article", "source-id": "15074", "openaccess": "0", "openaccessFlag": false}, {"@_fa": "true", "link": [{"@_fa": "true", "@ref": "self", "@href": "https://api.elsevier.com/content/abstract/scopus_id/84887070239"}, {"@_fa": "true", "@ref": "author-affiliation", "@href": "https://api.elsevier.com/content/abstract/scopus_id/84887070239?field=author,affiliation"}, {"@_fa": "true", "@ref": "scopus", "@href": "https://www.scopus.com/inward/record.uri?partnerID=HzOxMe3b&scp=84887070239&origin=inward"}, {"@_fa": "true", "@ref": "scopus-citedby", "@href": "https://www.scopus.com/inward/citedby.uri?partnerID=HzOxMe3b&scp=84887070239&origin=inward"}], "prism:url": "https://api.elsevier.com/content/abstract/scopus_id/84887070239", "dc:identifier": "SCOPUS_ID:84887070239", "eid": "2-s2.0-84887070239", "dc:title": "How user risk and requirements risk moderate the effects of formal and informal control on the process performance of IT projects", "dc:creator": "Keil M.", "prism:publicationName": "European Journal of Information Systems", "prism:issn": "0960085X", "prism:eIssn": "14769344", "prism:volume": "22", "prism:issueIdentifier": "6", "prism:pageRange": "650-672", "prism:coverDate": "2013-01-01", "prism:coverDisplayDate": "November 2013", "prism:doi": "10.1057/ejis.2012.42", "pii": "EJIS201242", "citedby-count": "94", "affiliation": [{"@_fa": "true", "affilname": "J. Mack Robinson College of Business", "affiliation-city": "Atlanta", "affiliation-country": "United States"}], "prism:aggregationType": "Journal", "subtype": "ar", "subtypeDescription": "Article", "source-id": "15074", "openaccess": "0", "openaccessFlag": false}, {"@_fa": "true", "link": [{"@_fa": "true", "@ref": "self", "@href": "https://api.elsevier.com/content/abstract/scopus_id/84887064864"}, {"@_fa": "true", "@ref": "author-affiliation", "@href": "https://api.elsevier.com/content/abstract/scopus_id/84887064864?field=author,affiliation"}, {"@_fa": "true", "@ref": "scopus", "@href": "https://www.scopus.com/inward/record.uri?partnerID=HzOxMe3b&scp=84887064864&origin=inward"}, {"@_fa": "true", "@ref": "scopus-citedby", "@href": "https://www.scopus.com/inward/citedby.uri?partnerID=HzOxMe3b&scp=84887064864&origin=inward"}], "prism:url": "https://api.elsevier.com/content/abstract/scopus_id/84887064864", "dc:identifier": "SCOPUS_ID:84887064864", "eid": "2-s2.0-84887064864", "dc:title": "Longitudinal use of method rationale in method configuration: An exploratory study", "dc:creator": "Karlsson F.", "prism:publicationName": "European Journal of Information Systems", "prism:issn": "0960085X", "prism:eIssn": "14769344", "prism:volume": "22", "prism:issueIdentifier": "6", "prism:pageRange": "690-710", "prism:coverDate": "2013-01-01", "prism:coverDisplayDate": "November 2013", "prism:doi": "10.1057/ejis.2012.30", "pii": "EJIS201230", "citedby-count": "7", "affiliation": [{"@_fa": "true", "affilname": "Handelsh\u00f6gskolan vid \u00d6rebro Universitet", "affiliation-city": "Orebro", "affiliation-country": "Sweden"}], "prism:aggregationType": "Journal", "subtype": "ar", "subtypeDescription": "Article", "source-id": "15074", "openaccess": "0", "openaccessFlag": false}, {"@_fa": "true", "link": [{"@_fa": "true", "@ref": "self", "@href": "https://api.elsevier.com/content/abstract/scopus_id/84887048678"}, {"@_fa": "true", "@ref": "author-affiliation", "@href": "https://api.elsevier.com/content/abstract/scopus_id/84887048678?field=author,affiliation"}, {"@_fa": "true", "@ref": "scopus", "@href": "https://www.scopus.com/inward/record.uri?partnerID=HzOxMe3b&scp=84887048678&origin=inward"}, {"@_fa": "true", "@ref": "scopus-citedby", "@href": "https://www.scopus.com/inward/citedby.uri?partnerID=HzOxMe3b&scp=84887048678&origin=inward"}], "prism:url": "https://api.elsevier.com/content/abstract/scopus_id/84887048678", "dc:identifier": "SCOPUS_ID:84887048678", "eid": "2-s2.0-84887048678", "dc:title": "The pursuit of trust in Ad hoc virtual teams: How much electronic portrayal is too much?", "dc:creator": "Altschuller S.", "prism:publicationName": "European Journal of Information Systems", "prism:issn": "0960085X", "prism:eIssn": "14769344", "prism:volume": "22", "prism:issueIdentifier": "6", "prism:pageRange": "619-636", "prism:coverDate": "2013-01-01", "prism:coverDisplayDate": "November 2013", "prism:doi": "10.1057/ejis.2012.39", "pii": "EJIS201239", "citedby-count": "19", "affiliation": [{"@_fa": "true", "affilname": "Hagan School of Business", "affiliation-city": "New Rochelle", "affiliation-country": "United States"}], "prism:aggregationType": "Journal", "subtype": "ar", "subtypeDescription": "Article", "source-id": "15074", "openaccess": "0", "openaccessFlag": false}, {"@_fa": "true", "link": [{"@_fa": "true", "@ref": "self", "@href": "https://api.elsevier.com/content/abstract/scopus_id/84883204876"}, {"@_fa": "true", "@ref": "author-affiliation", "@href": "https://api.elsevier.com/content/abstract/scopus_id/84883204876?field=author,affiliation"}, {"@_fa": "true", "@ref": "scopus", "@href": "https://www.scopus.com/inward/record.uri?partnerID=HzOxMe3b&scp=84883204876&origin=inward"}, {"@_fa": "true", "@ref": "scopus-citedby", "@href": "https://www.scopus.com/inward/citedby.uri?partnerID=HzOxMe3b&scp=84883204876&origin=inward"}], "prism:url": "https://api.elsevier.com/content/abstract/scopus_id/84883204876", "dc:identifier": "SCOPUS_ID:84883204876", "eid": "2-s2.0-84883204876", "dc:title": "Inter-firm IT governance in power-imbalanced buyer-supplier dyads: Exploring how it works and why it lasts", "dc:creator": "Xiao J.", "prism:publicationName": "European Journal of Information Systems", "prism:issn": "0960085X", "prism:eIssn": "14769344", "prism:volume": "22", "prism:issueIdentifier": "5", "prism:pageRange": "512-528", "prism:coverDate": "2013-01-01", "prism:coverDisplayDate": "September 2013", "prism:doi": "10.1057/ejis.2012.40", "pii": "EJIS201240", "citedby-count": "20", "affiliation": [{"@_fa": "true", "affilname": "Sun Yat-Sen University", "affiliation-city": "Guangzhou", "affiliation-country": "China"}], "prism:aggregationType": "Journal", "subtype": "ar", "subtypeDescription": "Article", "source-id": "15074", "openaccess": "0", "openaccessFlag": false}, {"@_fa": "true", "link": [{"@_fa": "true", "@ref": "self", "@href": "https://api.elsevier.com/content/abstract/scopus_id/84883200348"}, {"@_fa": "true", "@ref": "author-affiliation", "@href": "https://api.elsevier.com/content/abstract/scopus_id/84883200348?field=author,affiliation"}, {"@_fa": "true", "@ref": "scopus", "@href": "https://www.scopus.com/inward/record.uri?partnerID=HzOxMe3b&scp=84883200348&origin=inward"}, {"@_fa": "true", "@ref": "scopus-citedby", "@href": "https://www.scopus.com/inward/citedby.uri?partnerID=HzOxMe3b&scp=84883200348&origin=inward"}], "prism:url": "https://api.elsevier.com/content/abstract/scopus_id/84883200348", "dc:identifier": "SCOPUS_ID:84883200348", "eid": "2-s2.0-84883200348", "dc:title": "The mediating role of psychological contract breach in IS outsourcing: Inter-firm governance perspective", "dc:creator": "Kim H.J.", "prism:publicationName": "European Journal of Information Systems", "prism:issn": "0960085X", "prism:eIssn": "14769344", "prism:volume": "22", "prism:issueIdentifier": "5", "prism:pageRange": "529-547", "prism:coverDate": "2013-01-01", "prism:coverDisplayDate": "September 2013", "prism:doi": "10.1057/ejis.2012.41", "pii": "EJIS201241", "citedby-count": "29", "affiliation": [{"@_fa": "true", "affilname": "National University of Singapore", "affiliation-city": "Singapore City", "affiliation-country": "Singapore"}], "prism:aggregationType": "Journal", "subtype": "ar", "subtypeDescription": "Article", "source-id": "15074", "openaccess": "0", "openaccessFlag": false}, {"@_fa": "true", "link": [{"@_fa": "true", "@ref": "self", "@href": "https://api.elsevier.com/content/abstract/scopus_id/84883192243"}, {"@_fa": "true", "@ref": "author-affiliation", "@href": "https://api.elsevier.com/content/abstract/scopus_id/84883192243?field=author,affiliation"}, {"@_fa": "true", "@ref": "scopus", "@href": "https://www.scopus.com/inward/record.uri?partnerID=HzOxMe3b&scp=84883192243&origin=inward"}, {"@_fa": "true", "@ref": "scopus-citedby", "@href": "https://www.scopus.com/inward/citedby.uri?partnerID=HzOxMe3b&scp=84883192243&origin=inward"}], "prism:url": "https://api.elsevier.com/content/abstract/scopus_id/84883192243", "dc:identifier": "SCOPUS_ID:84883192243", "eid": "2-s2.0-84883192243", "dc:title": "Creating value through governing IT deployment in a public/private-sector inter-organisational context: A human agency perspective", "dc:creator": "Wilkin C.L.", "prism:publicationName": "European Journal of Information Systems", "prism:issn": "0960085X", "prism:eIssn": "14769344", "prism:volume": "22", "prism:issueIdentifier": "5", "prism:pageRange": "498-511", "prism:coverDate": "2013-01-01", "prism:coverDisplayDate": "September 2013", "prism:doi": "10.1057/ejis.2012.21", "pii": "EJIS201221", "citedby-count": "21", "affiliation": [{"@_fa": "true", "affilname": "Monash University", "affiliation-city": "Melbourne", "affiliation-country": "Australia"}], "prism:aggregationType": "Journal", "subtype": "ar", "subtypeDescription": "Article", "source-id": "15074", "openaccess": "0", "openaccessFlag": false}, {"@_fa": "true", "link": [{"@_fa": "true", "@ref": "self", "@href": "https://api.elsevier.com/content/abstract/scopus_id/84883179579"}, {"@_fa": "true", "@ref": "author-affiliation", "@href": "https://api.elsevier.com/content/abstract/scopus_id/84883179579?field=author,affiliation"}, {"@_fa": "true", "@ref": "scopus", "@href": "https://www.scopus.com/inward/record.uri?partnerID=HzOxMe3b&scp=84883179579&origin=inward"}, {"@_fa": "true", "@ref": "scopus-citedby", "@href": "https://www.scopus.com/inward/citedby.uri?partnerID=HzOxMe3b&scp=84883179579&origin=inward"}], "prism:url": "https://api.elsevier.com/content/abstract/scopus_id/84883179579", "dc:identifier": "SCOPUS_ID:84883179579", "eid": "2-s2.0-84883179579", "dc:title": "Governing IT in inter-organizational relationships: Issues and future research", "dc:creator": "Grant G.", "prism:publicationName": "European Journal of Information Systems", "prism:issn": "0960085X", "prism:eIssn": "14769344", "prism:volume": "22", "prism:issueIdentifier": "5", "prism:pageRange": "493-497", "prism:coverDate": "2013-01-01", "prism:coverDisplayDate": "September 2013", "prism:doi": "10.1057/ejis.2013.21", "pii": "EJIS201321", "citedby-count": "27", "affiliation": [{"@_fa": "true", "affilname": "Carleton University", "affiliation-city": "Ottawa", "affiliation-country": "Canada"}], "prism:aggregationType": "Journal", "subtype": "ed", "subtypeDescription": "Editorial", "source-id": "15074", "openaccess": "0", "openaccessFlag": false}, {"@_fa": "true", "link": [{"@_fa": "true", "@ref": "self", "@href": "https://api.elsevier.com/content/abstract/scopus_id/84883172581"}, {"@_fa": "true", "@ref": "author-affiliation", "@href": "https://api.elsevier.com/content/abstract/scopus_id/84883172581?field=author,affiliation"}, {"@_fa": "true", "@ref": "scopus", "@href": "https://www.scopus.com/inward/record.uri?partnerID=HzOxMe3b&scp=84883172581&origin=inward"}, {"@_fa": "true", "@ref": "scopus-citedby", "@href": "https://www.scopus.com/inward/citedby.uri?partnerID=HzOxMe3b&scp=84883172581&origin=inward"}], "prism:url": "https://api.elsevier.com/content/abstract/scopus_id/84883172581", "dc:identifier": "SCOPUS_ID:84883172581", "eid": "2-s2.0-84883172581", "dc:title": "Exploring value networks: Theorising the creation and capture of value with open source software", "dc:creator": "Morgan L.", "prism:publicationName": "European Journal of Information Systems", "prism:issn": "0960085X", "prism:eIssn": "14769344", "prism:volume": "22", "prism:issueIdentifier": "5", "prism:pageRange": "569-588", "prism:coverDate": "2013-01-01", "prism:coverDisplayDate": "September 2013", "prism:doi": "10.1057/ejis.2012.44", "pii": "EJIS201244", "citedby-count": "40", "affiliation": [{"@_fa": "true", "affilname": "Lero - The Irish Software Engineering Research Centre", "affiliation-city": "Limerick", "affiliation-country": "Ireland"}], "prism:aggregationType": "Journal", "subtype": "ar", "subtypeDescription": "Article", "source-id": "15074", "openaccess": "0", "openaccessFlag": false}, {"@_fa": "true", "link": [{"@_fa": "true", "@ref": "self", "@href": "https://api.elsevier.com/content/abstract/scopus_id/84883137947"}, {"@_fa": "true", "@ref": "author-affiliation", "@href": "https://api.elsevier.com/content/abstract/scopus_id/84883137947?field=author,affiliation"}, {"@_fa": "true", "@ref": "scopus", "@href": "https://www.scopus.com/inward/record.uri?partnerID=HzOxMe3b&scp=84883137947&origin=inward"}, {"@_fa": "true", "@ref": "scopus-citedby", "@href": "https://www.scopus.com/inward/citedby.uri?partnerID=HzOxMe3b&scp=84883137947&origin=inward"}], "prism:url": "https://api.elsevier.com/content/abstract/scopus_id/84883137947", "dc:identifier": "SCOPUS_ID:84883137947", "eid": "2-s2.0-84883137947", "dc:title": "Exploring the impact of operating model choice on the governance of inter-organizational workflow: The U.S. e-prescribing network", "dc:creator": "King N.", "prism:publicationName": "European Journal of Information Systems", "prism:issn": "0960085X", "prism:eIssn": "14769344", "prism:volume": "22", "prism:issueIdentifier": "5", "prism:pageRange": "548-568", "prism:coverDate": "2013-01-01", "prism:coverDisplayDate": "September 2013", "prism:doi": "10.1057/ejis.2012.47", "pii": "EJIS201247", "citedby-count": "18", "affiliation": [{"@_fa": "true", "affilname": "Suliman S. Olayan School of Business", "affiliation-city": "Beirut", "affiliation-country": "Lebanon"}], "prism:aggregationType": "Journal", "subtype": "ar", "subtypeDescription": "Article", "source-id": "15074", "openaccess": "0", "openaccessFlag": false}, {"@_fa": "true", "link": [{"@_fa": "true", "@ref": "self", "@href": "https://api.elsevier.com/content/abstract/scopus_id/84878927070"}, {"@_fa": "true", "@ref": "author-affiliation", "@href": "https://api.elsevier.com/content/abstract/scopus_id/84878927070?field=author,affiliation"}, {"@_fa": "true", "@ref": "scopus", "@href": "https://www.scopus.com/inward/record.uri?partnerID=HzOxMe3b&scp=84878927070&origin=inward"}, {"@_fa": "true", "@ref": "scopus-citedby", "@href": "https://www.scopus.com/inward/citedby.uri?partnerID=HzOxMe3b&scp=84878927070&origin=inward"}], "prism:url": "https://api.elsevier.com/content/abstract/scopus_id/84878927070", "dc:identifier": "SCOPUS_ID:84878927070", "eid": "2-s2.0-84878927070", "dc:title": "How a professionally qualified doctoral student bridged the practice-research gap: A confessional account of Collaborative Practice Research", "dc:creator": "Mathiassen L.", "prism:publicationName": "European Journal of Information Systems", "prism:issn": "0960085X", "prism:eIssn": "14769344", "prism:volume": "22", "prism:issueIdentifier": "4", "prism:pageRange": "475-492", "prism:coverDate": "2013-01-01", "prism:coverDisplayDate": "July 2013", "prism:doi": "10.1057/ejis.2012.35", "pii": "EJIS201235", "citedby-count": "18", "affiliation": [{"@_fa": "true", "affilname": "J. Mack Robinson College of Business", "affiliation-city": "Atlanta", "affiliation-country": "United States"}], "prism:aggregationType": "Journal", "subtype": "ar", "subtypeDescription": "Article", "source-id": "15074", "openaccess": "0", "openaccessFlag": false}, {"@_fa": "true", "link": [{"@_fa": "true", "@ref": "self", "@href": "https://api.elsevier.com/content/abstract/scopus_id/84878925410"}, {"@_fa": "true", "@ref": "author-affiliation", "@href": "https://api.elsevier.com/content/abstract/scopus_id/84878925410?field=author,affiliation"}, {"@_fa": "true", "@ref": "scopus", "@href": "https://www.scopus.com/inward/record.uri?partnerID=HzOxMe3b&scp=84878925410&origin=inward"}, {"@_fa": "true", "@ref": "scopus-citedby", "@href": "https://www.scopus.com/inward/citedby.uri?partnerID=HzOxMe3b&scp=84878925410&origin=inward"}], "prism:url": "https://api.elsevier.com/content/abstract/scopus_id/84878925410", "dc:identifier": "SCOPUS_ID:84878925410", "eid": "2-s2.0-84878925410", "dc:title": "The role of online seller reviews and product price on buyers' willingness-to-pay: A risk perspective", "dc:creator": "Wu J.", "prism:publicationName": "European Journal of Information Systems", "prism:issn": "0960085X", "prism:eIssn": "14769344", "prism:volume": "22", "prism:issueIdentifier": "4", "prism:pageRange": "416-433", "prism:coverDate": "2013-01-01", "prism:coverDisplayDate": "July 2013", "prism:doi": "10.1057/ejis.2012.33", "pii": "EJIS201233", "citedby-count": "30", "affiliation": [{"@_fa": "true", "affilname": "E. J. Ourso College of Business", "affiliation-city": "Baton Rouge", "affiliation-country": "United States"}], "prism:aggregationType": "Journal", "subtype": "ar", "subtypeDescription": "Article", "source-id": "15074", "openaccess": "0", "openaccessFlag": false}, {"@_fa": "true", "link": [{"@_fa": "true", "@ref": "self", "@href": "https://api.elsevier.com/content/abstract/scopus_id/84878920455"}, {"@_fa": "true", "@ref": "author-affiliation", "@href": "https://api.elsevier.com/content/abstract/scopus_id/84878920455?field=author,affiliation"}, {"@_fa": "true", "@ref": "scopus", "@href": "https://www.scopus.com/inward/record.uri?partnerID=HzOxMe3b&scp=84878920455&origin=inward"}, {"@_fa": "true", "@ref": "scopus-citedby", "@href": "https://www.scopus.com/inward/citedby.uri?partnerID=HzOxMe3b&scp=84878920455&origin=inward"}], "prism:url": "https://api.elsevier.com/content/abstract/scopus_id/84878920455", "dc:identifier": "SCOPUS_ID:84878920455", "eid": "2-s2.0-84878920455", "dc:title": "Information technology offshoring in India: A postcolonial perspective", "dc:creator": "Ravishankar M.N.", "prism:publicationName": "European Journal of Information Systems", "prism:issn": "0960085X", "prism:eIssn": "14769344", "prism:volume": "22", "prism:issueIdentifier": "4", "prism:pageRange": "387-402", "prism:coverDate": "2013-01-01", "prism:coverDisplayDate": "July 2013", "prism:doi": "10.1057/ejis.2012.32", "pii": "EJIS201232", "citedby-count": "57", "affiliation": [{"@_fa": "true", "affilname": "Loughborough University, School of Business and Economics", "affiliation-city": "Loughborough", "affiliation-country": "United Kingdom"}], "prism:aggregationType": "Journal", "subtype": "ar", "subtypeDescription": "Article", "source-id": "15074", "openaccess": "0", "openaccessFlag": false, "freetoread": {"value": [{"$": "all"}, {"$": "repository"}, {"$": "repositoryvor"}, {"$": "repositoryam"}]}, "freetoreadLabel": {"value": [{"$": "All Open Access"}, {"$": "Green"}]}}, {"@_fa": "true", "link": [{"@_fa": "true", "@ref": "self", "@href": "https://api.elsevier.com/content/abstract/scopus_id/84878914667"}, {"@_fa": "true", "@ref": "author-affiliation", "@href": "https://api.elsevier.com/content/abstract/scopus_id/84878914667?field=author,affiliation"}, {"@_fa": "true", "@ref": "scopus", "@href": "https://www.scopus.com/inward/record.uri?partnerID=HzOxMe3b&scp=84878914667&origin=inward"}, {"@_fa": "true", "@ref": "scopus-citedby", "@href": "https://www.scopus.com/inward/citedby.uri?partnerID=HzOxMe3b&scp=84878914667&origin=inward"}], "prism:url": "https://api.elsevier.com/content/abstract/scopus_id/84878914667", "dc:identifier": "SCOPUS_ID:84878914667", "eid": "2-s2.0-84878914667", "dc:title": "Towards integrating acceptance and resistance research: Evidence from a telecare case study", "dc:creator": "Van Offenbeek M.", "prism:publicationName": "European Journal of Information Systems", "prism:issn": "0960085X", "prism:eIssn": "14769344", "prism:volume": "22", "prism:issueIdentifier": "4", "prism:pageRange": "434-454", "prism:coverDate": "2013-01-01", "prism:coverDisplayDate": "July 2013", "prism:doi": "10.1057/ejis.2012.29", "pii": "EJIS201229", "citedby-count": "63", "affiliation": [{"@_fa": "true", "affilname": "Rijksuniversiteit Groningen", "affiliation-city": "Groningen", "affiliation-country": "Netherlands"}], "prism:aggregationType": "Journal", "subtype": "ar", "subtypeDescription": "Article", "source-id": "15074", "openaccess": "0", "openaccessFlag": false}, {"@_fa": "true", "link": [{"@_fa": "true", "@ref": "self", "@href": "https://api.elsevier.com/content/abstract/scopus_id/84878911368"}, {"@_fa": "true", "@ref": "author-affiliation", "@href": "https://api.elsevier.com/content/abstract/scopus_id/84878911368?field=author,affiliation"}, {"@_fa": "true", "@ref": "scopus", "@href": "https://www.scopus.com/inward/record.uri?partnerID=HzOxMe3b&scp=84878911368&origin=inward"}, {"@_fa": "true", "@ref": "scopus-citedby", "@href": "https://www.scopus.com/inward/citedby.uri?partnerID=HzOxMe3b&scp=84878911368&origin=inward"}], "prism:url": "https://api.elsevier.com/content/abstract/scopus_id/84878911368", "dc:identifier": "SCOPUS_ID:84878911368", "eid": "2-s2.0-84878911368", "dc:title": "Leveraging the IT competence of non-IS workers: Social exchange and the good corporate citizen", "dc:creator": "Davis J.M.", "prism:publicationName": "European Journal of Information Systems", "prism:issn": "0960085X", "prism:eIssn": "14769344", "prism:volume": "22", "prism:issueIdentifier": "4", "prism:pageRange": "403-415", "prism:coverDate": "2013-01-01", "prism:coverDisplayDate": "July 2013", "prism:doi": "10.1057/ejis.2012.36", "pii": "EJIS201236", "citedby-count": "21", "affiliation": [{"@_fa": "true", "affilname": "College of Charleston", "affiliation-city": "Charleston", "affiliation-country": "United States"}], "prism:aggregationType": "Journal", "subtype": "ar", "subtypeDescription": "Article", "source-id": "15074", "openaccess": "0", "openaccessFlag": false}, {"@_fa": "true", "link": [{"@_fa": "true", "@ref": "self", "@href": "https://api.elsevier.com/content/abstract/scopus_id/84878907037"}, {"@_fa": "true", "@ref": "author-affiliation", "@href": "https://api.elsevier.com/content/abstract/scopus_id/84878907037?field=author,affiliation"}, {"@_fa": "true", "@ref": "scopus", "@href": "https://www.scopus.com/inward/record.uri?partnerID=HzOxMe3b&scp=84878907037&origin=inward"}, {"@_fa": "true", "@ref": "scopus-citedby", "@href": "https://www.scopus.com/inward/citedby.uri?partnerID=HzOxMe3b&scp=84878907037&origin=inward"}], "prism:url": "https://api.elsevier.com/content/abstract/scopus_id/84878907037", "dc:identifier": "SCOPUS_ID:84878907037", "eid": "2-s2.0-84878907037", "dc:title": "'Datafication': Making sense of (big) data in a complex world", "dc:creator": "Lycett M.", "prism:publicationName": "European Journal of Information Systems", "prism:issn": "0960085X", "prism:eIssn": "14769344", "prism:volume": "22", "prism:issueIdentifier": "4", "prism:pageRange": "381-386", "prism:coverDate": "2013-01-01", "prism:coverDisplayDate": "July 2013", "prism:doi": "10.1057/ejis.2013.10", "pii": "EJIS201310", "citedby-count": "238", "affiliation": [{"@_fa": "true", "affilname": "Brunel University London", "affiliation-city": "Uxbridge", "affiliation-country": "United Kingdom"}], "prism:aggregationType": "Journal", "subtype": "re", "subtypeDescription": "Review", "source-id": "15074", "openaccess": "0", "openaccessFlag": false, "freetoread": {"value": [{"$": "all"}, {"$": "repository"}, {"$": "repositoryvor"}, {"$": "repositoryam"}]}, "freetoreadLabel": {"value": [{"$": "All Open Access"}, {"$": "Green"}]}}, {"@_fa": "true", "link": [{"@_fa": "true", "@ref": "self", "@href": "https://api.elsevier.com/content/abstract/scopus_id/84878904383"}, {"@_fa": "true", "@ref": "author-affiliation", "@href": "https://api.elsevier.com/content/abstract/scopus_id/84878904383?field=author,affiliation"}, {"@_fa": "true", "@ref": "scopus", "@href": "https://www.scopus.com/inward/record.uri?partnerID=HzOxMe3b&scp=84878904383&origin=inward"}, {"@_fa": "true", "@ref": "scopus-citedby", "@href": "https://www.scopus.com/inward/citedby.uri?partnerID=HzOxMe3b&scp=84878904383&origin=inward"}], "prism:url": "https://api.elsevier.com/content/abstract/scopus_id/84878904383", "dc:identifier": "SCOPUS_ID:84878904383", "eid": "2-s2.0-84878904383", "dc:title": "Trust dynamics in a large system implementation: Six theoretical propositions", "dc:creator": "Schlichter B.R.", "prism:publicationName": "European Journal of Information Systems", "prism:issn": "0960085X", "prism:eIssn": "14769344", "prism:volume": "22", "prism:issueIdentifier": "4", "prism:pageRange": "455-474", "prism:coverDate": "2013-01-01", "prism:coverDisplayDate": "July 2013", "prism:doi": "10.1057/ejis.2012.24", "pii": "EJIS201224", "citedby-count": "9", "affiliation": [{"@_fa": "true", "affilname": "Aarhus Universitet", "affiliation-city": "Aarhus", "affiliation-country": "Denmark"}], "prism:aggregationType": "Journal", "subtype": "ar", "subtypeDescription": "Article", "source-id": "15074", "openaccess": "0", "openaccessFlag": false}, {"@_fa": "true", "link": [{"@_fa": "true", "@ref": "self", "@href": "https://api.elsevier.com/content/abstract/scopus_id/84876398894"}, {"@_fa": "true", "@ref": "author-affiliation", "@href": "https://api.elsevier.com/content/abstract/scopus_id/84876398894?field=author,affiliation"}, {"@_fa": "true", "@ref": "scopus", "@href": "https://www.scopus.com/inward/record.uri?partnerID=HzOxMe3b&scp=84876398894&origin=inward"}, {"@_fa": "true", "@ref": "scopus-citedby", "@href": "https://www.scopus.com/inward/citedby.uri?partnerID=HzOxMe3b&scp=84876398894&origin=inward"}], "prism:url": "https://api.elsevier.com/content/abstract/scopus_id/84876398894", "dc:identifier": "SCOPUS_ID:84876398894", "eid": "2-s2.0-84876398894", "dc:title": "Digital business reporting standards: Mapping the battle in France", "dc:creator": "Guilloux V.", "prism:publicationName": "European Journal of Information Systems", "prism:issn": "0960085X", "prism:eIssn": "14769344", "prism:volume": "22", "prism:issueIdentifier": "3", "prism:pageRange": "257-277", "prism:coverDate": "2013-01-01", "prism:coverDisplayDate": "May 2013", "prism:doi": "10.1057/ejis.2012.5", "pii": "EJIS20125", "citedby-count": "22", "affiliation": [{"@_fa": "true", "affilname": "Universit\u00e9 Paris-Est Cr\u00e9teil", "affiliation-city": "Creteil", "affiliation-country": "France"}], "prism:aggregationType": "Journal", "subtype": "ar", "subtypeDescription": "Article", "source-id": "15074", "openaccess": "0", "openaccessFlag": false}, {"@_fa": "true", "link": [{"@_fa": "true", "@ref": "self", "@href": "https://api.elsevier.com/content/abstract/scopus_id/84876384441"}, {"@_fa": "true", "@ref": "author-affiliation", "@href": "https://api.elsevier.com/content/abstract/scopus_id/84876384441?field=author,affiliation"}, {"@_fa": "true", "@ref": "scopus", "@href": "https://www.scopus.com/inward/record.uri?partnerID=HzOxMe3b&scp=84876384441&origin=inward"}, {"@_fa": "true", "@ref": "scopus-citedby", "@href": "https://www.scopus.com/inward/citedby.uri?partnerID=HzOxMe3b&scp=84876384441&origin=inward"}], "prism:url": "https://api.elsevier.com/content/abstract/scopus_id/84876384441", "dc:identifier": "SCOPUS_ID:84876384441", "eid": "2-s2.0-84876384441", "dc:title": "Information privacy and correlates: An empirical attempt to bridge and distinguish privacyrelated concepts", "dc:creator": "Dinev T.", "prism:publicationName": "European Journal of Information Systems", "prism:issn": "0960085X", "prism:eIssn": "14769344", "prism:volume": "22", "prism:issueIdentifier": "3", "prism:pageRange": "295-316", "prism:coverDate": "2013-01-01", "prism:coverDisplayDate": "May 2013", "prism:doi": "10.1057/ejis.2012.23", "pii": "EJIS201223", "citedby-count": "221", "affiliation": [{"@_fa": "true", "affilname": "Florida Atlantic University", "affiliation-city": "Boca Raton", "affiliation-country": "United States"}], "prism:aggregationType": "Journal", "subtype": "ar", "subtypeDescription": "Article", "source-id": "15074", "openaccess": "0", "openaccessFlag": false}, {"@_fa": "true", "link": [{"@_fa": "true", "@ref": "self", "@href": "https://api.elsevier.com/content/abstract/scopus_id/84876366994"}, {"@_fa": "true", "@ref": "author-affiliation", "@href": "https://api.elsevier.com/content/abstract/scopus_id/84876366994?field=author,affiliation"}, {"@_fa": "true", "@ref": "scopus", "@href": "https://www.scopus.com/inward/record.uri?partnerID=HzOxMe3b&scp=84876366994&origin=inward"}, {"@_fa": "true", "@ref": "scopus-citedby", "@href": "https://www.scopus.com/inward/citedby.uri?partnerID=HzOxMe3b&scp=84876366994&origin=inward"}], "prism:url": "https://api.elsevier.com/content/abstract/scopus_id/84876366994", "dc:identifier": "SCOPUS_ID:84876366994", "eid": "2-s2.0-84876366994", "dc:title": "Sympathy or strategy: Social capital drivers for collaborative contributions to the IS community", "dc:creator": "Trier M.", "prism:publicationName": "European Journal of Information Systems", "prism:issn": "0960085X", "prism:eIssn": "14769344", "prism:volume": "22", "prism:issueIdentifier": "3", "prism:pageRange": "317-335", "prism:coverDate": "2013-01-01", "prism:coverDisplayDate": "May 2013", "prism:doi": "10.1057/ejis.2012.27", "pii": "EJIS201227", "citedby-count": "17", "affiliation": [{"@_fa": "true", "affilname": "Copenhagen Business School", "affiliation-city": "Frederiksberg", "affiliation-country": "Denmark"}], "prism:aggregationType": "Journal", "subtype": "ar", "subtypeDescription": "Article", "source-id": "15074", "openaccess": "0", "openaccessFlag": false}, {"@_fa": "true", "link": [{"@_fa": "true", "@ref": "self", "@href": "https://api.elsevier.com/content/abstract/scopus_id/84876356118"}, {"@_fa": "true", "@ref": "author-affiliation", "@href": "https://api.elsevier.com/content/abstract/scopus_id/84876356118?field=author,affiliation"}, {"@_fa": "true", "@ref": "scopus", "@href": "https://www.scopus.com/inward/record.uri?partnerID=HzOxMe3b&scp=84876356118&origin=inward"}, {"@_fa": "true", "@ref": "scopus-citedby", "@href": "https://www.scopus.com/inward/citedby.uri?partnerID=HzOxMe3b&scp=84876356118&origin=inward"}], "prism:url": "https://api.elsevier.com/content/abstract/scopus_id/84876356118", "dc:identifier": "SCOPUS_ID:84876356118", "eid": "2-s2.0-84876356118", "dc:title": "Top management support in multiple-project environments: An in-practice view", "dc:creator": "Elbanna A.", "prism:publicationName": "European Journal of Information Systems", "prism:issn": "0960085X", "prism:eIssn": "14769344", "prism:volume": "22", "prism:issueIdentifier": "3", "prism:pageRange": "278-294", "prism:coverDate": "2013-01-01", "prism:coverDisplayDate": "May 2013", "prism:doi": "10.1057/ejis.2012.16", "pii": "EJIS201216", "citedby-count": "51", "affiliation": [{"@_fa": "true", "affilname": "Royal Holloway, University of London", "affiliation-city": "Egham", "affiliation-country": "United Kingdom"}], "prism:aggregationType": "Journal", "subtype": "re", "subtypeDescription": "Review", "source-id": "15074", "openaccess": "0", "openaccessFlag": false}, {"@_fa": "true", "link": [{"@_fa": "true", "@ref": "self", "@href": "https://api.elsevier.com/content/abstract/scopus_id/84876350744"}, {"@_fa": "true", "@ref": "author-affiliation", "@href": "https://api.elsevier.com/content/abstract/scopus_id/84876350744?field=author,affiliation"}, {"@_fa": "true", "@ref": "scopus", "@href": "https://www.scopus.com/inward/record.uri?partnerID=HzOxMe3b&scp=84876350744&origin=inward"}, {"@_fa": "true", "@ref": "scopus-citedby", "@href": "https://www.scopus.com/inward/citedby.uri?partnerID=HzOxMe3b&scp=84876350744&origin=inward"}], "prism:url": "https://api.elsevier.com/content/abstract/scopus_id/84876350744", "dc:identifier": "SCOPUS_ID:84876350744", "eid": "2-s2.0-84876350744", "dc:title": "Can we have fun @ work? the role of intrinsic motivation for utilitarian systems", "dc:creator": "Gerow J.E.", "prism:publicationName": "European Journal of Information Systems", "prism:issn": "0960085X", "prism:eIssn": "14769344", "prism:volume": "22", "prism:issueIdentifier": "3", "prism:pageRange": "360-380", "prism:coverDate": "2013-01-01", "prism:coverDisplayDate": "May 2013", "prism:doi": "10.1057/ejis.2012.25", "pii": "EJIS201225", "citedby-count": "86", "affiliation": [{"@_fa": "true", "affilname": "Virginia Military Institute", "affiliation-city": "Lexington", "affiliation-country": "United States"}], "prism:aggregationType": "Journal", "subtype": "ar", "subtypeDescription": "Article", "source-id": "15074", "openaccess": "0", "openaccessFlag": false}, {"@_fa": "true", "link": [{"@_fa": "true", "@ref": "self", "@href": "https://api.elsevier.com/content/abstract/scopus_id/84876349896"}, {"@_fa": "true", "@ref": "author-affiliation", "@href": "https://api.elsevier.com/content/abstract/scopus_id/84876349896?field=author,affiliation"}, {"@_fa": "true", "@ref": "scopus", "@href": "https://www.scopus.com/inward/record.uri?partnerID=HzOxMe3b&scp=84876349896&origin=inward"}, {"@_fa": "true", "@ref": "scopus-citedby", "@href": "https://www.scopus.com/inward/citedby.uri?partnerID=HzOxMe3b&scp=84876349896&origin=inward"}], "prism:url": "https://api.elsevier.com/content/abstract/scopus_id/84876349896", "dc:identifier": "SCOPUS_ID:84876349896", "eid": "2-s2.0-84876349896", "dc:title": "Embracing diversity through mixed methods research", "dc:creator": "\u00c5gerfalk P.J.", "prism:publicationName": "European Journal of Information Systems", "prism:issn": "0960085X", "prism:eIssn": "14769344", "prism:volume": "22", "prism:issueIdentifier": "3", "prism:pageRange": "251-256", "prism:coverDate": "2013-01-01", "prism:coverDisplayDate": "May 2013", "prism:doi": "10.1057/ejis.2013.6", "pii": "EJIS20136", "citedby-count": "48", "prism:aggregationType": "Journal", "subtype": "re", "subtypeDescription": "Review", "source-id": "15074", "openaccess": "1", "openaccessFlag": true, "freetoread": {"value": [{"$": "all"}, {"$": "publisherfree2read"}]}, "freetoreadLabel": {"value": [{"$": "All Open Access"}, {"$": "Bronze"}]}}, {"@_fa": "true", "link": [{"@_fa": "true", "@ref": "self", "@href": "https://api.elsevier.com/content/abstract/scopus_id/84874625541"}, {"@_fa": "true", "@ref": "author-affiliation", "@href": "https://api.elsevier.com/content/abstract/scopus_id/84874625541?field=author,affiliation"}, {"@_fa": "true", "@ref": "scopus", "@href": "https://www.scopus.com/inward/record.uri?partnerID=HzOxMe3b&scp=84874625541&origin=inward"}, {"@_fa": "true", "@ref": "scopus-citedby", "@href": "https://www.scopus.com/inward/citedby.uri?partnerID=HzOxMe3b&scp=84874625541&origin=inward"}], "prism:url": "https://api.elsevier.com/content/abstract/scopus_id/84874625541", "dc:identifier": "SCOPUS_ID:84874625541", "eid": "2-s2.0-84874625541", "dc:title": "Research opportunities in information technology funding and system justification", "dc:creator": "Peffers K.", "prism:publicationName": "European Journal of Information Systems", "prism:issn": "0960085X", "prism:eIssn": "14769344", "prism:volume": "22", "prism:issueIdentifier": "2", "prism:pageRange": "131-138", "prism:coverDate": "2013-01-01", "prism:coverDisplayDate": "March 2013", "prism:doi": "10.1057/ejis.2012.60", "pii": "EJIS201260", "citedby-count": "10", "affiliation": [{"@_fa": "true", "affilname": "Lee Business School", "affiliation-city": "Las Vegas", "affiliation-country": "United States"}], "prism:aggregationType": "Journal", "subtype": "re", "subtypeDescription": "Review", "source-id": "15074", "openaccess": "0", "openaccessFlag": false}, {"@_fa": "true", "link": [{"@_fa": "true", "@ref": "self", "@href": "https://api.elsevier.com/content/abstract/scopus_id/84874623921"}, {"@_fa": "true", "@ref": "author-affiliation", "@href": "https://api.elsevier.com/content/abstract/scopus_id/84874623921?field=author,affiliation"}, {"@_fa": "true", "@ref": "scopus", "@href": "https://www.scopus.com/inward/record.uri?partnerID=HzOxMe3b&scp=84874623921&origin=inward"}, {"@_fa": "true", "@ref": "scopus-citedby", "@href": "https://www.scopus.com/inward/citedby.uri?partnerID=HzOxMe3b&scp=84874623921&origin=inward"}], "prism:url": "https://api.elsevier.com/content/abstract/scopus_id/84874623921", "dc:identifier": "SCOPUS_ID:84874623921", "eid": "2-s2.0-84874623921", "dc:title": "Shareholder reaction to firm investments in the capability maturity model: An event study", "dc:creator": "Filbeck G.", "prism:publicationName": "European Journal of Information Systems", "prism:issn": "0960085X", "prism:eIssn": "14769344", "prism:volume": "22", "prism:issueIdentifier": "2", "prism:pageRange": "170-190", "prism:coverDate": "2013-01-01", "prism:coverDisplayDate": "March 2013", "prism:doi": "10.1057/ejis.2012.54", "pii": "EJIS201254", "citedby-count": "8", "affiliation": [{"@_fa": "true", "affilname": "Black School of Business", "affiliation-city": "Erie", "affiliation-country": "United States"}], "prism:aggregationType": "Journal", "subtype": "ar", "subtypeDescription": "Article", "source-id": "15074", "openaccess": "0", "openaccessFlag": false}, {"@_fa": "true", "link": [{"@_fa": "true", "@ref": "self", "@href": "https://api.elsevier.com/content/abstract/scopus_id/84874621315"}, {"@_fa": "true", "@ref": "author-affiliation", "@href": "https://api.elsevier.com/content/abstract/scopus_id/84874621315?field=author,affiliation"}, {"@_fa": "true", "@ref": "scopus", "@href": "https://www.scopus.com/inward/record.uri?partnerID=HzOxMe3b&scp=84874621315&origin=inward"}, {"@_fa": "true", "@ref": "scopus-citedby", "@href": "https://www.scopus.com/inward/citedby.uri?partnerID=HzOxMe3b&scp=84874621315&origin=inward"}], "prism:url": "https://api.elsevier.com/content/abstract/scopus_id/84874621315", "dc:identifier": "SCOPUS_ID:84874621315", "eid": "2-s2.0-84874621315", "dc:title": "Effective ERP adoption processes: The role of project activators and resource investments", "dc:creator": "Bernroider E.W.N.", "prism:publicationName": "European Journal of Information Systems", "prism:issn": "0960085X", "prism:eIssn": "14769344", "prism:volume": "22", "prism:issueIdentifier": "2", "prism:pageRange": "235-250", "prism:coverDate": "2013-01-01", "prism:coverDisplayDate": "March 2013", "prism:doi": "10.1057/ejis.2012.51", "pii": "EJIS201251", "citedby-count": "15", "affiliation": [{"@_fa": "true", "affilname": "Wirtschaftsuniversit\u00e4t Wien", "affiliation-city": "Vienna", "affiliation-country": "Austria"}], "prism:aggregationType": "Journal", "subtype": "ar", "subtypeDescription": "Article", "source-id": "15074", "openaccess": "0", "openaccessFlag": false}, {"@_fa": "true", "link": [{"@_fa": "true", "@ref": "self", "@href": "https://api.elsevier.com/content/abstract/scopus_id/84874609667"}, {"@_fa": "true", "@ref": "author-affiliation", "@href": "https://api.elsevier.com/content/abstract/scopus_id/84874609667?field=author,affiliation"}, {"@_fa": "true", "@ref": "scopus", "@href": "https://www.scopus.com/inward/record.uri?partnerID=HzOxMe3b&scp=84874609667&origin=inward"}, {"@_fa": "true", "@ref": "scopus-citedby", "@href": "https://www.scopus.com/inward/citedby.uri?partnerID=HzOxMe3b&scp=84874609667&origin=inward"}], "prism:url": "https://api.elsevier.com/content/abstract/scopus_id/84874609667", "dc:identifier": "SCOPUS_ID:84874609667", "eid": "2-s2.0-84874609667", "dc:title": "Effects of time-inconsistent preferences on information technology infrastructure investments with growth options", "dc:creator": "Khan S.S.", "prism:publicationName": "European Journal of Information Systems", "prism:issn": "0960085X", "prism:eIssn": "14769344", "prism:volume": "22", "prism:issueIdentifier": "2", "prism:pageRange": "206-220", "prism:coverDate": "2013-01-01", "prism:coverDisplayDate": "March 2013", "prism:doi": "10.1057/ejis.2012.4", "pii": "EJIS20124", "citedby-count": "11", "affiliation": [{"@_fa": "true", "affilname": "The University of North Carolina at Charlotte", "affiliation-city": "Charlotte", "affiliation-country": "United States"}], "prism:aggregationType": "Journal", "subtype": "ar", "subtypeDescription": "Article", "source-id": "15074", "openaccess": "0", "openaccessFlag": false}, {"@_fa": "true", "link": [{"@_fa": "true", "@ref": "self", "@href": "https://api.elsevier.com/content/abstract/scopus_id/84874606072"}, {"@_fa": "true", "@ref": "author-affiliation", "@href": "https://api.elsevier.com/content/abstract/scopus_id/84874606072?field=author,affiliation"}, {"@_fa": "true", "@ref": "scopus", "@href": "https://www.scopus.com/inward/record.uri?partnerID=HzOxMe3b&scp=84874606072&origin=inward"}, {"@_fa": "true", "@ref": "scopus-citedby", "@href": "https://www.scopus.com/inward/citedby.uri?partnerID=HzOxMe3b&scp=84874606072&origin=inward"}], "prism:url": "https://api.elsevier.com/content/abstract/scopus_id/84874606072", "dc:identifier": "SCOPUS_ID:84874606072", "eid": "2-s2.0-84874606072", "dc:title": "Adapting funding processes for agile IT projects: An empirical investigation", "dc:creator": "Cao L.", "prism:publicationName": "European Journal of Information Systems", "prism:issn": "0960085X", "prism:eIssn": "14769344", "prism:volume": "22", "prism:issueIdentifier": "2", "prism:pageRange": "191-205", "prism:coverDate": "2013-01-01", "prism:coverDisplayDate": "March 2013", "prism:doi": "10.1057/ejis.2012.9", "pii": "EJIS20129", "citedby-count": "40", "affiliation": [{"@_fa": "true", "affilname": "Old Dominion University", "affiliation-city": "Norfolk", "affiliation-country": "United States"}], "prism:aggregationType": "Journal", "subtype": "ar", "subtypeDescription": "Article", "source-id": "15074", "openaccess": "0", "openaccessFlag": false}, {"@_fa": "true", "link": [{"@_fa": "true", "@ref": "self", "@href": "https://api.elsevier.com/content/abstract/scopus_id/84874586939"}, {"@_fa": "true", "@ref": "author-affiliation", "@href": "https://api.elsevier.com/content/abstract/scopus_id/84874586939?field=author,affiliation"}, {"@_fa": "true", "@ref": "scopus", "@href": "https://www.scopus.com/inward/record.uri?partnerID=HzOxMe3b&scp=84874586939&origin=inward"}, {"@_fa": "true", "@ref": "scopus-citedby", "@href": "https://www.scopus.com/inward/citedby.uri?partnerID=HzOxMe3b&scp=84874586939&origin=inward"}], "prism:url": "https://api.elsevier.com/content/abstract/scopus_id/84874586939", "dc:identifier": "SCOPUS_ID:84874586939", "eid": "2-s2.0-84874586939", "dc:title": "E-government adoption in public administration organizations: Integrating institutional theory perspective and resource-based view", "dc:creator": "Zheng D.", "prism:publicationName": "European Journal of Information Systems", "prism:issn": "0960085X", "prism:eIssn": "14769344", "prism:volume": "22", "prism:issueIdentifier": "2", "prism:pageRange": "221-234", "prism:coverDate": "2013-01-01", "prism:coverDisplayDate": "March 2013", "prism:doi": "10.1057/ejis.2012.28", "pii": "EJIS201228", "citedby-count": "56", "affiliation": [{"@_fa": "true", "affilname": "Shanghai University of Finance and Economics", "affiliation-city": "Shanghai", "affiliation-country": "China"}], "prism:aggregationType": "Journal", "subtype": "ar", "subtypeDescription": "Article", "source-id": "15074", "openaccess": "0", "openaccessFlag": false}, {"@_fa": "true", "link": [{"@_fa": "true", "@ref": "self", "@href": "https://api.elsevier.com/content/abstract/scopus_id/84870289048"}, {"@_fa": "true", "@ref": "author-affiliation", "@href": "https://api.elsevier.com/content/abstract/scopus_id/84870289048?field=author,affiliation"}, {"@_fa": "true", "@ref": "scopus", "@href": "https://www.scopus.com/inward/record.uri?partnerID=HzOxMe3b&scp=84870289048&origin=inward"}, {"@_fa": "true", "@ref": "scopus-citedby", "@href": "https://www.scopus.com/inward/citedby.uri?partnerID=HzOxMe3b&scp=84870289048&origin=inward"}], "prism:url": "https://api.elsevier.com/content/abstract/scopus_id/84870289048", "dc:identifier": "SCOPUS_ID:84870289048", "eid": "2-s2.0-84870289048", "dc:title": "Enriching our theoretical repertoire: The role of evolutionary psychology in technology acceptance", "dc:creator": "Abraham C.", "prism:publicationName": "European Journal of Information Systems", "prism:issn": "0960085X", "prism:eIssn": "14769344", "prism:volume": "22", "prism:issueIdentifier": "1", "prism:pageRange": "56-75", "prism:coverDate": "2013-01-01", "prism:coverDisplayDate": "January 2013", "prism:doi": "10.1057/ejis.2011.25", "pii": "EJIS201125", "citedby-count": "29", "affiliation": [{"@_fa": "true", "affilname": "Raymond A. Mason School of Business", "affiliation-city": "Williamsburg", "affiliation-country": "United States"}], "prism:aggregationType": "Journal", "subtype": "ar", "subtypeDescription": "Article", "source-id": "15074", "openaccess": "0", "openaccessFlag": false}, {"@_fa": "true", "link": [{"@_fa": "true", "@ref": "self", "@href": "https://api.elsevier.com/content/abstract/scopus_id/84870284015"}, {"@_fa": "true", "@ref": "author-affiliation", "@href": "https://api.elsevier.com/content/abstract/scopus_id/84870284015?field=author,affiliation"}, {"@_fa": "true", "@ref": "scopus", "@href": "https://www.scopus.com/inward/record.uri?partnerID=HzOxMe3b&scp=84870284015&origin=inward"}, {"@_fa": "true", "@ref": "scopus-citedby", "@href": "https://www.scopus.com/inward/citedby.uri?partnerID=HzOxMe3b&scp=84870284015&origin=inward"}], "prism:url": "https://api.elsevier.com/content/abstract/scopus_id/84870284015", "dc:identifier": "SCOPUS_ID:84870284015", "eid": "2-s2.0-84870284015", "dc:title": "Grounded theorizing for electronically mediated social contexts", "dc:creator": "Vaast E.", "prism:publicationName": "European Journal of Information Systems", "prism:issn": "0960085X", "prism:eIssn": "14769344", "prism:volume": "22", "prism:issueIdentifier": "1", "prism:pageRange": "9-25", "prism:coverDate": "2013-01-01", "prism:coverDisplayDate": "January 2013", "prism:doi": "10.1057/ejis.2011.26", "pii": "EJIS201126", "citedby-count": "46", "affiliation": [{"@_fa": "true", "affilname": "Desautels Faculty of Management", "affiliation-city": "Montreal", "affiliation-country": "Canada"}], "prism:aggregationType": "Journal", "subtype": "ar", "subtypeDescription": "Article", "source-id": "15074", "openaccess": "0", "openaccessFlag": false}, {"@_fa": "true", "link": [{"@_fa": "true", "@ref": "self", "@href": "https://api.elsevier.com/content/abstract/scopus_id/84870279555"}, {"@_fa": "true", "@ref": "author-affiliation", "@href": "https://api.elsevier.com/content/abstract/scopus_id/84870279555?field=author,affiliation"}, {"@_fa": "true", "@ref": "scopus", "@href": "https://www.scopus.com/inward/record.uri?partnerID=HzOxMe3b&scp=84870279555&origin=inward"}, {"@_fa": "true", "@ref": "scopus-citedby", "@href": "https://www.scopus.com/inward/citedby.uri?partnerID=HzOxMe3b&scp=84870279555&origin=inward"}], "prism:url": "https://api.elsevier.com/content/abstract/scopus_id/84870279555", "dc:identifier": "SCOPUS_ID:84870279555", "eid": "2-s2.0-84870279555", "dc:title": "Using grounded theory as a method for rigorously reviewing literature", "dc:creator": "Wolfswinkel J.F.", "prism:publicationName": "European Journal of Information Systems", "prism:issn": "0960085X", "prism:eIssn": "14769344", "prism:volume": "22", "prism:issueIdentifier": "1", "prism:pageRange": "45-55", "prism:coverDate": "2013-01-01", "prism:coverDisplayDate": "January 2013", "prism:doi": "10.1057/ejis.2011.51", "pii": "EJIS201151", "citedby-count": "416", "affiliation": [{"@_fa": "true", "affilname": "Universiteit Twente", "affiliation-city": "Enschede", "affiliation-country": "Netherlands"}], "prism:aggregationType": "Journal", "subtype": "re", "subtypeDescription": "Review", "source-id": "15074", "openaccess": "0", "openaccessFlag": false}, {"@_fa": "true", "link": [{"@_fa": "true", "@ref": "self", "@href": "https://api.elsevier.com/content/abstract/scopus_id/84870279069"}, {"@_fa": "true", "@ref": "author-affiliation", "@href": "https://api.elsevier.com/content/abstract/scopus_id/84870279069?field=author,affiliation"}, {"@_fa": "true", "@ref": "scopus", "@href": "https://www.scopus.com/inward/record.uri?partnerID=HzOxMe3b&scp=84870279069&origin=inward"}, {"@_fa": "true", "@ref": "scopus-citedby", "@href": "https://www.scopus.com/inward/citedby.uri?partnerID=HzOxMe3b&scp=84870279069&origin=inward"}], "prism:url": "https://api.elsevier.com/content/abstract/scopus_id/84870279069", "dc:identifier": "SCOPUS_ID:84870279069", "eid": "2-s2.0-84870279069", "dc:title": "Using a grounded theory approach to study online collaboration behaviors", "dc:creator": "Gasson S.", "prism:publicationName": "European Journal of Information Systems", "prism:issn": "0960085X", "prism:eIssn": "14769344", "prism:volume": "22", "prism:issueIdentifier": "1", "prism:pageRange": "95-118", "prism:coverDate": "2013-01-01", "prism:coverDisplayDate": "January 2013", "prism:doi": "10.1057/ejis.2011.24", "pii": "EJIS201124", "citedby-count": "39", "affiliation": [{"@_fa": "true", "affilname": "Drexel University", "affiliation-city": "Philadelphia", "affiliation-country": "United States"}], "prism:aggregationType": "Journal", "subtype": "ar", "subtypeDescription": "Article", "source-id": "15074", "openaccess": "0", "openaccessFlag": false}, {"@_fa": "true", "link": [{"@_fa": "true", "@ref": "self", "@href": "https://api.elsevier.com/content/abstract/scopus_id/84870274958"}, {"@_fa": "true", "@ref": "author-affiliation", "@href": "https://api.elsevier.com/content/abstract/scopus_id/84870274958?field=author,affiliation"}, {"@_fa": "true", "@ref": "scopus", "@href": "https://www.scopus.com/inward/record.uri?partnerID=HzOxMe3b&scp=84870274958&origin=inward"}, {"@_fa": "true", "@ref": "scopus-citedby", "@href": "https://www.scopus.com/inward/citedby.uri?partnerID=HzOxMe3b&scp=84870274958&origin=inward"}], "prism:url": "https://api.elsevier.com/content/abstract/scopus_id/84870274958", "dc:identifier": "SCOPUS_ID:84870274958", "eid": "2-s2.0-84870274958", "dc:title": "Profiling grounded theory approaches in information systems research", "dc:creator": "Matavire R.", "prism:publicationName": "European Journal of Information Systems", "prism:issn": "0960085X", "prism:eIssn": "14769344", "prism:volume": "22", "prism:issueIdentifier": "1", "prism:pageRange": "119-129", "prism:coverDate": "2013-01-01", "prism:coverDisplayDate": "January 2013", "prism:doi": "10.1057/ejis.2011.35", "pii": "EJIS201135", "citedby-count": "75", "affiliation": [{"@_fa": "true", "affilname": "University of Cape Town", "affiliation-city": "Cape Town", "affiliation-country": "South Africa"}], "prism:aggregationType": "Journal", "subtype": "ar", "subtypeDescription": "Article", "source-id": "15074", "openaccess": "0", "openaccessFlag": false}, {"@_fa": "true", "link": [{"@_fa": "true", "@ref": "self", "@href": "https://api.elsevier.com/content/abstract/scopus_id/84870265723"}, {"@_fa": "true", "@ref": "author-affiliation", "@href": "https://api.elsevier.com/content/abstract/scopus_id/84870265723?field=author,affiliation"}, {"@_fa": "true", "@ref": "scopus", "@href": "https://www.scopus.com/inward/record.uri?partnerID=HzOxMe3b&scp=84870265723&origin=inward"}, {"@_fa": "true", "@ref": "scopus-citedby", "@href": "https://www.scopus.com/inward/citedby.uri?partnerID=HzOxMe3b&scp=84870265723&origin=inward"}], "prism:url": "https://api.elsevier.com/content/abstract/scopus_id/84870265723", "dc:identifier": "SCOPUS_ID:84870265723", "eid": "2-s2.0-84870265723", "dc:title": "Grounded theory method in information systems research: Its nature, diversity and opportunities", "dc:creator": "Birks D.F.", "prism:publicationName": "European Journal of Information Systems", "prism:issn": "0960085X", "prism:eIssn": "14769344", "prism:volume": "22", "prism:issueIdentifier": "1", "prism:pageRange": "1-8", "prism:coverDate": "2013-01-01", "prism:coverDisplayDate": "January 2013", "prism:doi": "10.1057/ejis.2012.48", "pii": "EJIS201248", "citedby-count": "104", "affiliation": [{"@_fa": "true", "affilname": "University of Winchester", "affiliation-city": "Winchester", "affiliation-country": "United Kingdom"}], "prism:aggregationType": "Journal", "subtype": "re", "subtypeDescription": "Review", "source-id": "15074", "openaccess": "0", "openaccessFlag": false}, {"@_fa": "true", "link": [{"@_fa": "true", "@ref": "self", "@href": "https://api.elsevier.com/content/abstract/scopus_id/84870260509"}, {"@_fa": "true", "@ref": "author-affiliation", "@href": "https://api.elsevier.com/content/abstract/scopus_id/84870260509?field=author,affiliation"}, {"@_fa": "true", "@ref": "scopus", "@href": "https://www.scopus.com/inward/record.uri?partnerID=HzOxMe3b&scp=84870260509&origin=inward"}, {"@_fa": "true", "@ref": "scopus-citedby", "@href": "https://www.scopus.com/inward/citedby.uri?partnerID=HzOxMe3b&scp=84870260509&origin=inward"}], "prism:url": "https://api.elsevier.com/content/abstract/scopus_id/84870260509", "dc:identifier": "SCOPUS_ID:84870260509", "eid": "2-s2.0-84870260509", "dc:title": "Everyday power struggles: Living in an IOIS project", "dc:creator": "Hekkala R.", "prism:publicationName": "European Journal of Information Systems", "prism:issn": "0960085X", "prism:eIssn": "14769344", "prism:volume": "22", "prism:issueIdentifier": "1", "prism:pageRange": "76-94", "prism:coverDate": "2013-01-01", "prism:coverDisplayDate": "January 2013", "prism:doi": "10.1057/ejis.2012.43", "pii": "EJIS201243", "citedby-count": "35", "affiliation": [{"@_fa": "true", "affilname": "Aalto University School of Business", "affiliation-city": "Espoo", "affiliation-country": "Finland"}], "prism:aggregationType": "Journal", "subtype": "re", "subtypeDescription": "Review", "source-id": "15074", "openaccess": "0", "openaccessFlag": false}, {"@_fa": "true", "link": [{"@_fa": "true", "@ref": "self", "@href": "https://api.elsevier.com/content/abstract/scopus_id/84865859605"}, {"@_fa": "true", "@ref": "author-affiliation", "@href": "https://api.elsevier.com/content/abstract/scopus_id/84865859605?field=author,affiliation"}, {"@_fa": "true", "@ref": "scopus", "@href": "https://www.scopus.com/inward/record.uri?partnerID=HzOxMe3b&scp=84865859605&origin=inward"}, {"@_fa": "true", "@ref": "scopus-citedby", "@href": "https://www.scopus.com/inward/citedby.uri?partnerID=HzOxMe3b&scp=84865859605&origin=inward"}], "prism:url": "https://api.elsevier.com/content/abstract/scopus_id/84865859605", "dc:identifier": "SCOPUS_ID:84865859605", "eid": "2-s2.0-84865859605", "dc:title": "A method for taxonomy development and its application in information systems", "dc:creator": "Nickerson R.C.", "prism:publicationName": "European Journal of Information Systems", "prism:issn": "0960085X", "prism:eIssn": "14769344", "prism:volume": "22", "prism:issueIdentifier": "3", "prism:pageRange": "336-359", "prism:coverDate": "2013-01-01", "prism:coverDisplayDate": "May 2013", "prism:doi": "10.1057/ejis.2012.26", "pii": "EJIS201226", "citedby-count": "466", "affiliation": [{"@_fa": "true", "affilname": "San Francisco State University", "affiliation-city": "San Francisco", "affiliation-country": "United States"}], "prism:aggregationType": "Journal", "subtype": "ar", "subtypeDescription": "Article", "source-id": "15074", "openaccess": "0", "openaccessFlag": false}, {"@_fa": "true", "link": [{"@_fa": "true", "@ref": "self", "@href": "https://api.elsevier.com/content/abstract/scopus_id/84865839127"}, {"@_fa": "true", "@ref": "author-affiliation", "@href": "https://api.elsevier.com/content/abstract/scopus_id/84865839127?field=author,affiliation"}, {"@_fa": "true", "@ref": "scopus", "@href": "https://www.scopus.com/inward/record.uri?partnerID=HzOxMe3b&scp=84865839127&origin=inward"}, {"@_fa": "true", "@ref": "scopus-citedby", "@href": "https://www.scopus.com/inward/citedby.uri?partnerID=HzOxMe3b&scp=84865839127&origin=inward"}], "prism:url": "https://api.elsevier.com/content/abstract/scopus_id/84865839127", "dc:identifier": "SCOPUS_ID:84865839127", "eid": "2-s2.0-84865839127", "dc:title": "Revisiting IS business value research: What we already know, what we still need to know, and how we can get there", "dc:creator": "Schryen G.", "prism:publicationName": "European Journal of Information Systems", "prism:issn": "0960085X", "prism:eIssn": "14769344", "prism:volume": "22", "prism:issueIdentifier": "2", "prism:pageRange": "139-169", "prism:coverDate": "2013-01-01", "prism:coverDisplayDate": "March 2013", "prism:doi": "10.1057/ejis.2012.45", "pii": "EJIS201245", "citedby-count": "262", "affiliation": [{"@_fa": "true", "affilname": "Universit\u00e4t Regensburg", "affiliation-city": "Regensburg", "affiliation-country": "Germany"}], "prism:aggregationType": "Journal", "subtype": "re", "subtypeDescription": "Review", "source-id": "15074", "openaccess": "0", "openaccessFlag": false, "freetoread": {"value": [{"$": "all"}, {"$": "repository"}, {"$": "repositoryvor"}]}, "freetoreadLabel": {"value": [{"$": "All Open Access"}, {"$": "Green"}]}}, {"@_fa": "true", "link": [{"@_fa": "true", "@ref": "self", "@href": "https://api.elsevier.com/content/abstract/scopus_id/84865839121"}, {"@_fa": "true", "@ref": "author-affiliation", "@href": "https://api.elsevier.com/content/abstract/scopus_id/84865839121?field=author,affiliation"}, {"@_fa": "true", "@ref": "scopus", "@href": "https://www.scopus.com/inward/record.uri?partnerID=HzOxMe3b&scp=84865839121&origin=inward"}, {"@_fa": "true", "@ref": "scopus-citedby", "@href": "https://www.scopus.com/inward/citedby.uri?partnerID=HzOxMe3b&scp=84865839121&origin=inward"}], "prism:url": "https://api.elsevier.com/content/abstract/scopus_id/84865839121", "dc:identifier": "SCOPUS_ID:84865839121", "eid": "2-s2.0-84865839121", "dc:title": "The use of ethnography and grounded theory in the development of a management information system", "dc:creator": "Mattarelli E.", "prism:publicationName": "European Journal of Information Systems", "prism:issn": "0960085X", "prism:eIssn": "14769344", "prism:volume": "22", "prism:issueIdentifier": "1", "prism:pageRange": "26-44", "prism:coverDate": "2013-01-01", "prism:coverDisplayDate": "January 2013", "prism:doi": "10.1057/ejis.2011.34", "pii": "EJIS201134", "citedby-count": "16", "affiliation": [{"@_fa": "true", "affilname": "Universit\u00e0 degli Studi di Modena e Reggio Emilia", "affiliation-city": "Modena", "affiliation-country": "Italy"}], "prism:aggregationType": "Journal", "subtype": "ar", "subtypeDescription": "Article", "source-id": "15074", "openaccess": "0", "openaccessFlag": false}]}}