{"search-results": {"opensearch:totalResults": "44", "opensearch:startIndex": "0", "opensearch:itemsPerPage": "44", "opensearch:Query": {"@role": "request", "@searchTerms": "issn(03064573)", "@startPage": "0"}, "link": [{"@_fa": "true", "@ref": "self", "@href": "https://api.elsevier.com/content/search/scopus?start=0&count=200&query=issn%2803064573%29&date=2002&httpAccept=application/json&apiKey=ad4e12568b69167a2d25213b52923901&insttoken=0363e8707601cf3e7f27138d2b25f9e4", "@type": "application/json"}, {"@_fa": "true", "@ref": "first", "@href": "https://api.elsevier.com/content/search/scopus?start=0&count=200&query=issn%2803064573%29&date=2002&httpAccept=application/json&apiKey=ad4e12568b69167a2d25213b52923901&insttoken=0363e8707601cf3e7f27138d2b25f9e4", "@type": "application/json"}], "entry": [{"@_fa": "true", "prism:url": "https://api.elsevier.com/content/abstract/scopus_id/0036833224", "dc:identifier": "SCOPUS_ID:0036833224", "dc:title": "In vitro evaluation of a program for machine-aided indexing", "dc:creator": "Jacquemin C.", "prism:publicationName": "Information Processing and Management", "prism:issn": "03064573", "prism:volume": "38", "prism:issueIdentifier": "6", "prism:pageRange": "765-792", "prism:coverDate": "2002-11-01", "prism:doi": "10.1016/S0306-4573(01)00050-4", "citedby-count": "5", "affiliation": [{"@_fa": "true", "affiliation-country": "France"}, {"@_fa": "true", "affiliation-country": "France"}, {"@_fa": "true", "affiliation-country": "France"}], "authkeywords": "Controlled indexing | Free indexing | Human evaluation | Key-phrase indexing | Machine-aided indexing | Multi-word terms", "openaccess": "0", "openaccessFlag": false}, {"@_fa": "true", "prism:url": "https://api.elsevier.com/content/abstract/scopus_id/0036833196", "dc:identifier": "SCOPUS_ID:0036833196", "dc:title": "A test of genetic algorithms in relevance feedback", "dc:creator": "L\u00f3pez-Pujalte C.", "prism:publicationName": "Information Processing and Management", "prism:issn": "03064573", "prism:volume": "38", "prism:issueIdentifier": "6", "prism:pageRange": "793-805", "prism:coverDate": "2002-11-01", "prism:doi": "10.1016/S0306-4573(01)00061-9", "citedby-count": "35", "affiliation": [{"@_fa": "true", "affiliation-country": "Spain"}, {"@_fa": "true", "affiliation-country": "Spain"}], "authkeywords": "Genetic algorithms | Information retrieval | Relevance feedback | Test collections", "fund-sponsor": "European Social Fund", "openaccess": "0", "openaccessFlag": false, "freetoread": {"value": [{"$": "all"}, {"$": "repository"}, {"$": "repositoryvor"}]}, "freetoreadLabel": {"value": [{"$": "All Open Access"}, {"$": "Green"}]}}, {"@_fa": "true", "prism:url": "https://api.elsevier.com/content/abstract/scopus_id/0036833176", "dc:identifier": "SCOPUS_ID:0036833176", "dc:title": "A new method for selecting english field association terms of compound words and its knowledge representation", "dc:creator": "Atlam E.", "prism:publicationName": "Information Processing and Management", "prism:issn": "03064573", "prism:volume": "38", "prism:issueIdentifier": "6", "prism:pageRange": "807-821", "prism:coverDate": "2002-11-01", "prism:doi": "10.1016/S0306-4573(01)00062-0", "citedby-count": "31", "affiliation": [{"@_fa": "true", "affiliation-country": "Japan"}], "authkeywords": "Compound terms | Field association term | Redundant candidates | Semantic classification", "openaccess": "0", "openaccessFlag": false}, {"@_fa": "true", "prism:url": "https://api.elsevier.com/content/abstract/scopus_id/0036833175", "dc:identifier": "SCOPUS_ID:0036833175", "dc:title": "An information retrieval model based on vector space method by supervised learning", "dc:creator": "Tai X.", "prism:publicationName": "Information Processing and Management", "prism:issn": "03064573", "prism:volume": "38", "prism:issueIdentifier": "6", "prism:pageRange": "749-764", "prism:coverDate": "2002-11-01", "prism:doi": "10.1016/S0306-4573(01)00053-X", "citedby-count": "24", "affiliation": [{"@_fa": "true", "affiliation-country": "Japan"}], "authkeywords": "Information retrieval | Linear transformation | Relevance feedback | Singular value decomposition | Supervised learning | Vector space model", "openaccess": "0", "openaccessFlag": false}, {"@_fa": "true", "prism:url": "https://api.elsevier.com/content/abstract/scopus_id/0036833171", "dc:identifier": "SCOPUS_ID:0036833171", "dc:title": "Interpolation of the extended Boolean retrieval model", "dc:creator": "Zanger D.", "prism:publicationName": "Information Processing and Management", "prism:issn": "03064573", "prism:volume": "38", "prism:issueIdentifier": "6", "prism:pageRange": "743-748", "prism:coverDate": "2002-11-01", "prism:doi": "10.1016/S0306-4573(02)00023-7", "citedby-count": "1", "affiliation": [{"@_fa": "true", "affiliation-country": "United States"}], "authkeywords": "Extended Boolean model | Information retrieval | Interpolation of linear operators | p-norm", "openaccess": "0", "openaccessFlag": false}, {"@_fa": "true", "prism:url": "https://api.elsevier.com/content/abstract/scopus_id/0036833167", "dc:identifier": "SCOPUS_ID:0036833167", "dc:title": "Strong similarity measures for ordered sets of documents in information retrieval", "dc:creator": "Egghe L.", "prism:publicationName": "Information Processing and Management", "prism:issn": "03064573", "prism:volume": "38", "prism:issueIdentifier": "6", "prism:pageRange": "823-848", "prism:coverDate": "2002-11-01", "prism:doi": "10.1016/S0306-4573(01)00051-6", "citedby-count": "27", "affiliation": [{"@_fa": "true", "affiliation-country": "France"}, {"@_fa": "true", "affiliation-country": "Belgium"}, {"@_fa": "true", "affiliation-country": "Belgium"}], "openaccess": "0", "openaccessFlag": false, "freetoread": {"value": [{"$": "all"}, {"$": "repository"}, {"$": "repositoryam"}]}, "freetoreadLabel": {"value": [{"$": "All Open Access"}, {"$": "Green"}]}}, {"@_fa": "true", "prism:url": "https://api.elsevier.com/content/abstract/scopus_id/0036722224", "dc:identifier": "SCOPUS_ID:0036722224", "dc:title": "Differences and similarities in information seeking: Children and adults as Web users", "dc:creator": "Bilal D.", "prism:publicationName": "Information Processing and Management", "prism:issn": "03064573", "prism:volume": "38", "prism:issueIdentifier": "5", "prism:pageRange": "649-670", "prism:coverDate": "2002-09-01", "prism:doi": "10.1016/S0306-4573(01)00057-7", "citedby-count": "193", "affiliation": [{"@_fa": "true", "affiliation-country": "United States"}], "openaccess": "0", "openaccessFlag": false, "freetoread": {"value": [{"$": "all"}, {"$": "repository"}, {"$": "repositoryvor"}]}, "freetoreadLabel": {"value": [{"$": "All Open Access"}, {"$": "Green"}]}}, {"@_fa": "true", "prism:url": "https://api.elsevier.com/content/abstract/scopus_id/0036722217", "dc:identifier": "SCOPUS_ID:0036722217", "dc:title": "Toward a theoretical framework for understanding the relationship between situated action and planned action models of behavior in information retrieval contexts: Contributions from phenomenology", "dc:creator": "Ng K.", "prism:publicationName": "Information Processing and Management", "prism:issn": "03064573", "prism:volume": "38", "prism:issueIdentifier": "5", "prism:pageRange": "613-626", "prism:coverDate": "2002-09-01", "prism:doi": "10.1016/S0306-4573(01)00055-3", "citedby-count": "12", "affiliation": [{"@_fa": "true", "affiliation-country": "United States"}], "authkeywords": "Context | Planned action | Situated action theory | Typicality", "openaccess": "0", "openaccessFlag": false}, {"@_fa": "true", "prism:url": "https://api.elsevier.com/content/abstract/scopus_id/0036722215", "dc:identifier": "SCOPUS_ID:0036722215", "dc:title": "Users' relevance criteria in image retrieval in American history", "dc:creator": "Choi Y.", "prism:publicationName": "Information Processing and Management", "prism:issn": "03064573", "prism:volume": "38", "prism:issueIdentifier": "5", "prism:pageRange": "695-726", "prism:coverDate": "2002-09-01", "prism:doi": "10.1016/S0306-4573(01)00059-0", "citedby-count": "88", "affiliation": [{"@_fa": "true", "affiliation-country": "United States"}, {"@_fa": "true", "affiliation-country": "United States"}], "authkeywords": "Image retrieval | Information-seeking behavior | Relevance judgments", "openaccess": "0", "openaccessFlag": false}, {"@_fa": "true", "prism:url": "https://api.elsevier.com/content/abstract/scopus_id/0036722214", "dc:identifier": "SCOPUS_ID:0036722214", "dc:title": "An experiment in building profiles in information filtering: The role of context of user relevance feedback", "dc:creator": "Quiroga L.", "prism:publicationName": "Information Processing and Management", "prism:issn": "03064573", "prism:volume": "38", "prism:issueIdentifier": "5", "prism:pageRange": "671-694", "prism:coverDate": "2002-09-01", "prism:doi": "10.1016/S0306-4573(01)00058-9", "citedby-count": "27", "affiliation": [{"@_fa": "true", "affiliation-country": "United States"}, {"@_fa": "true", "affiliation-country": "United States"}], "authkeywords": "Information filtering | Relevance feedback judgments | User models | User profiles", "openaccess": "0", "openaccessFlag": false}, {"@_fa": "true", "prism:url": "https://api.elsevier.com/content/abstract/scopus_id/0036722213", "dc:identifier": "SCOPUS_ID:0036722213", "dc:title": "Traditional IR for web users: A context for general audience digital libraries", "dc:creator": "Wolfram D.", "prism:publicationName": "Information Processing and Management", "prism:issn": "03064573", "prism:volume": "38", "prism:issueIdentifier": "5", "prism:pageRange": "627-648", "prism:coverDate": "2002-09-01", "prism:doi": "10.1016/S0306-4573(01)00056-5", "citedby-count": "17", "affiliation": [{"@_fa": "true", "affiliation-country": "United States"}], "authkeywords": "Digital libraries | Information retrieval context | Internet searching | User studies", "openaccess": "0", "openaccessFlag": false}, {"@_fa": "true", "prism:url": "https://api.elsevier.com/content/abstract/scopus_id/0036643028", "dc:identifier": "SCOPUS_ID:0036643028", "dc:title": "A feature mining based approach for the classification of text documents into disjoint classes", "dc:creator": "Nieto S\u00e1nchez S.", "prism:publicationName": "Information Processing and Management", "prism:issn": "03064573", "prism:volume": "38", "prism:issueIdentifier": "4", "prism:pageRange": "583-604", "prism:coverDate": "2002-07-01", "prism:doi": "10.1016/S0306-4573(01)00049-8", "citedby-count": "19", "affiliation": [{"@_fa": "true", "affiliation-country": "United States"}], "authkeywords": "Data mining | Document classification | Document indexing | Machine learning | One Clause At a Time (OCAT) algorithm | Vector space model", "fund-sponsor": "Office of Naval Research", "openaccess": "0", "openaccessFlag": false}, {"@_fa": "true", "prism:url": "https://api.elsevier.com/content/abstract/scopus_id/0036643018", "dc:identifier": "SCOPUS_ID:0036643018", "dc:title": "Efficient stemmer generation", "dc:creator": "Fox B.", "prism:publicationName": "Information Processing and Management", "prism:issn": "03064573", "prism:volume": "38", "prism:issueIdentifier": "4", "prism:pageRange": "547-558", "prism:coverDate": "2002-07-01", "prism:doi": "10.1016/S0306-4573(01)00047-4", "citedby-count": "7", "affiliation": [{"@_fa": "true", "affiliation-country": "United States"}], "authkeywords": "Algorithms | Automatic indexing | Stemming", "openaccess": "0", "openaccessFlag": false}, {"@_fa": "true", "prism:url": "https://api.elsevier.com/content/abstract/scopus_id/0036643016", "dc:identifier": "SCOPUS_ID:0036643016", "dc:title": "Integrated multi-strategic Web document pre-processing for sentence and word boundary detection", "dc:creator": "Shim J.", "prism:publicationName": "Information Processing and Management", "prism:issn": "03064573", "prism:volume": "38", "prism:issueIdentifier": "4", "prism:pageRange": "509-527", "prism:coverDate": "2002-07-01", "prism:doi": "10.1016/S0306-4573(01)00044-9", "citedby-count": "4", "affiliation": [{"@_fa": "true", "affiliation-country": "South Korea"}, {"@_fa": "true", "affiliation-country": "South Korea"}], "authkeywords": "Sentence boundary disambiguation | Spacing-word correction | Text normalization | Word boundary disambiguation", "openaccess": "0", "openaccessFlag": false}, {"@_fa": "true", "prism:url": "https://api.elsevier.com/content/abstract/scopus_id/0036643014", "dc:identifier": "SCOPUS_ID:0036643014", "dc:title": "The effectiveness of query-specific hierarchic clustering in information retrieval", "dc:creator": "Tombros A.", "prism:publicationName": "Information Processing and Management", "prism:issn": "03064573", "prism:volume": "38", "prism:issueIdentifier": "4", "prism:pageRange": "559-582", "prism:coverDate": "2002-07-01", "prism:doi": "10.1016/S0306-4573(01)00048-6", "citedby-count": "122", "affiliation": [{"@_fa": "true", "affiliation-country": "United Kingdom"}], "authkeywords": "Effectiveness evaluation | Information retrieval | Query-specific hierarchic clustering", "fund-sponsor": "Engineering and Physical Sciences Research Council", "openaccess": "0", "openaccessFlag": false}, {"@_fa": "true", "prism:url": "https://api.elsevier.com/content/abstract/scopus_id/0036643012", "dc:identifier": "SCOPUS_ID:0036643012", "dc:title": "Analysis of large data logs: An application of Poisson sampling on excite web queries", "dc:creator": "Ozmutlu H.", "prism:publicationName": "Information Processing and Management", "prism:issn": "03064573", "prism:volume": "38", "prism:issueIdentifier": "4", "prism:pageRange": "473-490", "prism:coverDate": "2002-07-01", "prism:doi": "10.1016/S0306-4573(01)00043-7", "citedby-count": "35", "affiliation": [{"@_fa": "true", "affiliation-country": "Turkey"}, {"@_fa": "true", "affiliation-country": "United States"}], "authkeywords": "Data mining | Large-scale in depth data analysis | Poisson sampling | Search engine queries | Web user modeling", "openaccess": "0", "openaccessFlag": false, "freetoread": {"value": [{"$": "all"}, {"$": "repository"}, {"$": "repositoryvor"}]}, "freetoreadLabel": {"value": [{"$": "All Open Access"}, {"$": "Green"}]}}, {"@_fa": "true", "prism:url": "https://api.elsevier.com/content/abstract/scopus_id/0036643010", "dc:identifier": "SCOPUS_ID:0036643010", "dc:title": "The use of bigrams to enhance text categorization", "dc:creator": "Tan C.", "prism:publicationName": "Information Processing and Management", "prism:issn": "03064573", "prism:volume": "38", "prism:issueIdentifier": "4", "prism:pageRange": "529-546", "prism:coverDate": "2002-07-01", "prism:doi": "10.1016/S0306-4573(01)00045-0", "citedby-count": "179", "affiliation": [{"@_fa": "true", "affiliation-country": "United States"}, {"@_fa": "true", "affiliation-country": "South Korea"}], "authkeywords": "Information retrieval | Machine learning | Text categorization | Text classification", "fund-sponsor": "National Science Foundation", "openaccess": "0", "openaccessFlag": false, "freetoread": {"value": [{"$": "all"}, {"$": "repository"}, {"$": "repositoryam"}]}, "freetoreadLabel": {"value": [{"$": "All Open Access"}, {"$": "Green"}]}}, {"@_fa": "true", "prism:url": "https://api.elsevier.com/content/abstract/scopus_id/0036643004", "dc:identifier": "SCOPUS_ID:0036643004", "dc:title": "Characteristics of question format web queries: An exploratory study", "dc:creator": "Spink A.", "prism:publicationName": "Information Processing and Management", "prism:issn": "03064573", "prism:volume": "38", "prism:issueIdentifier": "4", "prism:pageRange": "453-471", "prism:coverDate": "2002-07-01", "prism:doi": "10.1016/S0306-4573(01)00042-5", "citedby-count": "48", "affiliation": [{"@_fa": "true", "affiliation-country": "Turkey"}, {"@_fa": "true", "affiliation-country": "United States"}], "openaccess": "0", "openaccessFlag": false, "freetoread": {"value": [{"$": "all"}, {"$": "repository"}, {"$": "repositoryvor"}, {"$": "repositoryam"}]}, "freetoreadLabel": {"value": [{"$": "All Open Access"}, {"$": "Green"}]}}, {"@_fa": "true", "prism:url": "https://api.elsevier.com/content/abstract/scopus_id/0036643003", "dc:identifier": "SCOPUS_ID:0036643003", "dc:title": "Mining a Web Citation Database for author co-citation analysis", "dc:creator": "He Y.", "prism:publicationName": "Information Processing and Management", "prism:issn": "03064573", "prism:volume": "38", "prism:issueIdentifier": "4", "prism:pageRange": "491-508", "prism:coverDate": "2002-07-01", "prism:doi": "10.1016/S0306-4573(01)00046-2", "citedby-count": "68", "affiliation": [{"@_fa": "true", "affiliation-country": "Singapore"}], "authkeywords": "Author co-citation analysis | Data mining | Intelligent information retrieval | Web Citation Database", "openaccess": "0", "openaccessFlag": false}, {"@_fa": "true", "prism:url": "https://api.elsevier.com/content/abstract/scopus_id/0036567935", "dc:identifier": "SCOPUS_ID:0036567935", "dc:title": "Gender differences in collaborative Web searching behavior: An elementary school study", "dc:creator": "Large A.", "prism:publicationName": "Information Processing and Management", "prism:issn": "03064573", "prism:volume": "38", "prism:issueIdentifier": "3", "prism:pageRange": "427-443", "prism:coverDate": "2002-05-01", "prism:doi": "10.1016/S0306-4573(01)00034-6", "citedby-count": "135", "affiliation": [{"@_fa": "true", "affiliation-country": "Canada"}], "authkeywords": "Children | Gender | Information-seeking behavior | Web", "fund-sponsor": "Social Sciences and Humanities Research Council of Canada", "openaccess": "0", "openaccessFlag": false}, {"@_fa": "true", "prism:url": "https://api.elsevier.com/content/abstract/scopus_id/0036567933", "dc:identifier": "SCOPUS_ID:0036567933", "dc:title": "Text classification using ESC-based stochastic decision lists", "dc:creator": "Li H.", "prism:publicationName": "Information Processing and Management", "prism:issn": "03064573", "prism:volume": "38", "prism:issueIdentifier": "3", "prism:pageRange": "343-361", "prism:coverDate": "2002-05-01", "prism:doi": "10.1016/S0306-4573(01)00038-3", "citedby-count": "18", "affiliation": [{"@_fa": "true", "affiliation-country": "China"}, {"@_fa": "true", "affiliation-country": "Japan"}], "authkeywords": "Extended stochastic complexity | Rule-based method | Statistical learning | Stochastic decision list | Text classification", "openaccess": "0", "openaccessFlag": false}, {"@_fa": "true", "prism:url": "https://api.elsevier.com/content/abstract/scopus_id/0036567932", "dc:identifier": "SCOPUS_ID:0036567932", "dc:title": "An experimental study on the iso-content-based angle similarity measure", "dc:creator": "Zhang J.", "prism:publicationName": "Information Processing and Management", "prism:issn": "03064573", "prism:volume": "38", "prism:issueIdentifier": "3", "prism:pageRange": "325-342", "prism:coverDate": "2002-05-01", "prism:doi": "10.1016/S0306-4573(01)00035-8", "citedby-count": "2", "affiliation": [{"@_fa": "true", "affiliation-country": "United States"}, {"@_fa": "true", "affiliation-country": "United States"}], "authkeywords": "Evaluation | Experiment | Iso-content-based angle similarity measure | Similarity analysis", "openaccess": "0", "openaccessFlag": false}, {"@_fa": "true", "prism:url": "https://api.elsevier.com/content/abstract/scopus_id/0036567931", "dc:identifier": "SCOPUS_ID:0036567931", "dc:title": "A user-centered approach to evaluating human interaction with Web search engines: An exploratory study", "dc:creator": "Spink A.", "prism:publicationName": "Information Processing and Management", "prism:issn": "03064573", "prism:volume": "38", "prism:issueIdentifier": "3", "prism:pageRange": "401-426", "prism:coverDate": "2002-05-01", "prism:doi": "10.1016/S0306-4573(01)00036-X", "citedby-count": "96", "affiliation": [{"@_fa": "true", "affiliation-country": "United States"}], "openaccess": "0", "openaccessFlag": false, "freetoread": {"value": [{"$": "all"}, {"$": "repository"}, {"$": "repositoryvor"}]}, "freetoreadLabel": {"value": [{"$": "All Open Access"}, {"$": "Green"}]}}, {"@_fa": "true", "prism:url": "https://api.elsevier.com/content/abstract/scopus_id/0036567930", "dc:identifier": "SCOPUS_ID:0036567930", "dc:title": "Support vector machines: Relevance feedback and information retrieval", "dc:creator": "Drucker H.", "prism:publicationName": "Information Processing and Management", "prism:issn": "03064573", "prism:volume": "38", "prism:issueIdentifier": "3", "prism:pageRange": "305-323", "prism:coverDate": "2002-05-01", "prism:doi": "10.1016/S0306-4573(01)00037-1", "citedby-count": "52", "affiliation": [{"@_fa": "true", "affiliation-country": "United States"}, {"@_fa": "true", "affiliation-country": "United States"}], "authkeywords": "Ide dec-hi | Information retrieval | Relevancy feedback | Rocchio | Support vector machines", "openaccess": "0", "openaccessFlag": false}, {"@_fa": "true", "prism:url": "https://api.elsevier.com/content/abstract/scopus_id/0036567929", "dc:identifier": "SCOPUS_ID:0036567929", "dc:title": "The cascade of interactions in the digital library interface", "dc:creator": "Bates M.", "prism:publicationName": "Information Processing and Management", "prism:issn": "03064573", "prism:volume": "38", "prism:issueIdentifier": "3", "prism:pageRange": "381-400", "prism:coverDate": "2002-05-01", "prism:doi": "10.1016/S0306-4573(01)00041-3", "citedby-count": "48", "affiliation": [{"@_fa": "true", "affiliation-country": "United States"}], "authkeywords": "Digital library design | Information retrieval systems | Information system design | Interface design | Online information systems", "openaccess": "0", "openaccessFlag": false}, {"@_fa": "true", "prism:url": "https://api.elsevier.com/content/abstract/scopus_id/0036567928", "dc:identifier": "SCOPUS_ID:0036567928", "dc:title": "Exemplary documents: A foundation for information retrieval design", "dc:creator": "Blair D.", "prism:publicationName": "Information Processing and Management", "prism:issn": "03064573", "prism:volume": "38", "prism:issueIdentifier": "3", "prism:pageRange": "363-379", "prism:coverDate": "2002-05-01", "prism:doi": "10.1016/S0306-4573(01)00027-9", "citedby-count": "23", "affiliation": [{"@_fa": "true", "affiliation-country": "United States"}, {"@_fa": "true", "affiliation-country": "United States"}], "fund-sponsor": "National Science Foundation", "openaccess": "0", "openaccessFlag": false}, {"@_fa": "true", "prism:url": "https://api.elsevier.com/content/abstract/scopus_id/0036497429", "dc:identifier": "SCOPUS_ID:0036497429", "dc:title": "The challenge of commercial document retrieval, Part I: Major issues, and a framework based on search exhaustivity, determinacy of representation and document collection size", "dc:creator": "Blair D.", "prism:publicationName": "Information Processing and Management", "prism:issn": "03064573", "prism:volume": "38", "prism:issueIdentifier": "2", "prism:pageRange": "273-291", "prism:coverDate": "2002-03-01", "prism:doi": "10.1016/S0306-4573(01)00024-3", "citedby-count": "35", "affiliation": [{"@_fa": "true", "affiliation-country": "United States"}], "openaccess": "0", "openaccessFlag": false}, {"@_fa": "true", "prism:url": "https://api.elsevier.com/content/abstract/scopus_id/0036497418", "dc:identifier": "SCOPUS_ID:0036497418", "dc:title": "The challenge of commercial document retrieval, Part II: A strategy for document searching based on identifiable document partitions", "dc:creator": "Blair D.", "prism:publicationName": "Information Processing and Management", "prism:issn": "03064573", "prism:volume": "38", "prism:issueIdentifier": "2", "prism:pageRange": "293-304", "prism:coverDate": "2002-03-01", "prism:doi": "10.1016/S0306-4573(01)00025-5", "citedby-count": "20", "affiliation": [{"@_fa": "true", "affiliation-country": "United States"}], "openaccess": "0", "openaccessFlag": false}, {"@_fa": "true", "prism:url": "https://api.elsevier.com/content/abstract/scopus_id/0036497405", "dc:identifier": "SCOPUS_ID:0036497405", "dc:title": "Problems of music information retrieval in the real world", "dc:creator": "Byrd D.", "prism:publicationName": "Information Processing and Management", "prism:issn": "03064573", "prism:volume": "38", "prism:issueIdentifier": "2", "prism:pageRange": "249-272", "prism:coverDate": "2002-03-01", "prism:doi": "10.1016/S0306-4573(01)00033-4", "citedby-count": "77", "affiliation": [{"@_fa": "true", "affiliation-country": "United States"}, {"@_fa": "true", "affiliation-country": "United Kingdom"}], "authkeywords": "Audio | Information retrieval | MIDI | Music | Notation | Searching", "fund-sponsor": "U.S. Department of Commerce", "openaccess": "0", "openaccessFlag": false}, {"@_fa": "true", "prism:url": "https://api.elsevier.com/content/abstract/scopus_id/0036497393", "dc:identifier": "SCOPUS_ID:0036497393", "dc:title": "Indexing aids at corporate websites: The use of robots.txt and META tags", "dc:creator": "Carl Drott M.", "prism:publicationName": "Information Processing and Management", "prism:issn": "03064573", "prism:volume": "38", "prism:issueIdentifier": "2", "prism:pageRange": "209-219", "prism:coverDate": "2002-03-01", "prism:doi": "10.1016/S0306-4573(01)00039-5", "citedby-count": "32", "affiliation": [{"@_fa": "true", "affiliation-country": "United States"}, {"@_fa": "true", "affiliation-country": "Hungary"}], "authkeywords": "Corporate web sites | Document access | Web indexing", "openaccess": "0", "openaccessFlag": false}, {"@_fa": "true", "prism:url": "https://api.elsevier.com/content/abstract/scopus_id/0036497390", "dc:identifier": "SCOPUS_ID:0036497390", "dc:title": "An evaluation method of words tendency depending on time-series variation and its improvements", "dc:creator": "Atlam E.", "prism:publicationName": "Information Processing and Management", "prism:issn": "03064573", "prism:volume": "38", "prism:issueIdentifier": "2", "prism:pageRange": "157-171", "prism:coverDate": "2002-03-01", "prism:doi": "10.1016/S0306-4573(01)00028-0", "citedby-count": "8", "affiliation": [{"@_fa": "true", "affiliation-country": "Japan"}], "authkeywords": "CNN newspaper | Decision tree | Time-series variation | Words popularity", "fund-sponsor": "Ministry of Higher Education", "openaccess": "0", "openaccessFlag": false}, {"@_fa": "true", "prism:url": "https://api.elsevier.com/content/abstract/scopus_id/0036722218", "dc:identifier": "SCOPUS_ID:0036722218", "dc:title": "Issues of context in information retrieval (IR): An introduction to the special issue", "dc:creator": "Cool C.", "prism:publicationName": "Information Processing and Management", "prism:issn": "03064573", "prism:volume": "38", "prism:issueIdentifier": "5", "prism:pageRange": "605-611", "prism:coverDate": "2002-01-01", "prism:doi": "10.1016/S0306-4573(01)00054-1", "citedby-count": "60", "affiliation": [{"@_fa": "true", "affiliation-country": "United States"}, {"@_fa": "true", "affiliation-country": "United States"}], "authkeywords": "Context in information retrieval | Interactive information retrieval", "openaccess": "0", "openaccessFlag": false}, {"@_fa": "true", "prism:url": "https://api.elsevier.com/content/abstract/scopus_id/0036722216", "dc:identifier": "SCOPUS_ID:0036722216", "dc:title": "Combining evidence for automatic Web session identification", "dc:creator": "He D.", "prism:publicationName": "Information Processing and Management", "prism:issn": "03064573", "prism:volume": "38", "prism:issueIdentifier": "5", "prism:pageRange": "727-742", "prism:coverDate": "2002-01-01", "prism:doi": "10.1016/S0306-4573(01)00060-7", "citedby-count": "145", "affiliation": [{"@_fa": "true", "affiliation-country": "United Kingdom"}], "authkeywords": "Dempster-Shafer theory | Search context | Session identification | Web user logs", "fund-sponsor": "Engineering and Physical Sciences Research Council", "openaccess": "0", "openaccessFlag": false}, {"@_fa": "true", "prism:url": "https://api.elsevier.com/content/abstract/scopus_id/0036567934", "dc:identifier": "SCOPUS_ID:0036567934", "dc:title": "Some thoughts on the reported results of TREC", "dc:creator": "Blair D.", "prism:publicationName": "Information Processing and Management", "prism:issn": "03064573", "prism:volume": "38", "prism:issueIdentifier": "3", "prism:pageRange": "445-451", "prism:coverDate": "2002-01-01", "prism:doi": "10.1016/S0306-4573(01)00026-7", "citedby-count": "11", "affiliation": [{"@_fa": "true", "affiliation-country": "United States"}], "openaccess": "0", "openaccessFlag": false}, {"@_fa": "true", "prism:url": "https://api.elsevier.com/content/abstract/scopus_id/0036497404", "dc:identifier": "SCOPUS_ID:0036497404", "dc:title": "Extraction of field-coherent passages", "dc:creator": "Lee S.", "prism:publicationName": "Information Processing and Management", "prism:issn": "03064573", "prism:volume": "38", "prism:issueIdentifier": "2", "prism:pageRange": "173-207", "prism:coverDate": "2002-01-01", "prism:doi": "10.1016/S0306-4573(01)00032-2", "citedby-count": "25", "affiliation": [{"@_fa": "true", "affiliation-country": "Japan"}], "authkeywords": "Document classification | Field-associated term | Topic matter: continuity and transition", "openaccess": "0", "openaccessFlag": false}, {"@_fa": "true", "prism:url": "https://api.elsevier.com/content/abstract/scopus_id/0036497403", "dc:identifier": "SCOPUS_ID:0036497403", "dc:title": "A dynamic construction algorithm for the Compact Patricia trie using the hierarchical structure", "dc:creator": "Jung M.", "prism:publicationName": "Information Processing and Management", "prism:issn": "03064573", "prism:volume": "38", "prism:issueIdentifier": "2", "prism:pageRange": "221-236", "prism:coverDate": "2002-01-01", "prism:doi": "10.1016/S0306-4573(01)00031-0", "citedby-count": "6", "affiliation": [{"@_fa": "true", "affiliation-country": "Japan"}], "authkeywords": "Access method | Data structure | Hierarchical structure | Information retrieval | Patricia trie", "openaccess": "0", "openaccessFlag": false}, {"@_fa": "true", "prism:url": "https://api.elsevier.com/content/abstract/scopus_id/0036497402", "dc:identifier": "SCOPUS_ID:0036497402", "dc:title": "The applicability of universal pragmatics in information retrieval interaction: A pilot study", "dc:creator": "Ng K.", "prism:publicationName": "Information Processing and Management", "prism:issn": "03064573", "prism:volume": "38", "prism:issueIdentifier": "2", "prism:pageRange": "237-248", "prism:coverDate": "2002-01-01", "prism:doi": "10.1016/S0306-4573(01)00030-9", "citedby-count": "3", "affiliation": [{"@_fa": "true", "affiliation-country": "United States"}], "authkeywords": "Dialogic model | Human computer interaction | Universal pragmatics", "openaccess": "0", "openaccessFlag": false}, {"@_fa": "true", "prism:url": "https://api.elsevier.com/content/abstract/scopus_id/0036028157", "dc:identifier": "SCOPUS_ID:0036028157", "dc:title": "Assessing bias in search engines", "dc:creator": "Mowshowitz A.", "prism:publicationName": "Information Processing and Management", "prism:issn": "03064573", "prism:volume": "38", "prism:issueIdentifier": "1", "prism:pageRange": "141-156", "prism:coverDate": "2002-01-01", "prism:doi": "10.1016/S0306-4573(01)00020-6", "citedby-count": "51", "affiliation": [{"@_fa": "true", "affiliation-country": "United States"}], "authkeywords": "Bias | Retrieval performance | Search engines | System measurement", "openaccess": "0", "openaccessFlag": false}, {"@_fa": "true", "prism:url": "https://api.elsevier.com/content/abstract/scopus_id/0036028156", "dc:identifier": "SCOPUS_ID:0036028156", "dc:title": "Visualizing a high recall search strategy output for undergraduates in an exploration stage of researching a term paper", "dc:creator": "Cole C.", "prism:publicationName": "Information Processing and Management", "prism:issn": "03064573", "prism:volume": "38", "prism:issueIdentifier": "1", "prism:pageRange": "37-54", "prism:coverDate": "2002-01-01", "prism:doi": "10.1016/S0306-4573(01)00029-2", "citedby-count": "11", "affiliation": [{"@_fa": "true", "affiliation-country": "Canada"}, {"@_fa": "true", "affiliation-country": "Canada"}], "authkeywords": "Cartographic maps | Information need | Information retrieval | Information seeking | Information visualization", "fund-sponsor": "Social Sciences and Humanities Research Council of Canada", "openaccess": "0", "openaccessFlag": false}, {"@_fa": "true", "prism:url": "https://api.elsevier.com/content/abstract/scopus_id/0036028155", "dc:identifier": "SCOPUS_ID:0036028155", "dc:title": "Patterns between interactive intentions and information-seeking strategies", "dc:creator": "Xie H.", "prism:publicationName": "Information Processing and Management", "prism:issn": "03064573", "prism:volume": "38", "prism:issueIdentifier": "1", "prism:pageRange": "55-77", "prism:coverDate": "2002-01-01", "prism:doi": "10.1016/S0306-4573(01)00018-8", "citedby-count": "40", "affiliation": [{"@_fa": "true", "affiliation-country": "United States"}], "authkeywords": "Information retrieval | Information retrieval system | Information-seeking strategy | Interactive intention | Pattern | User goal", "openaccess": "0", "openaccessFlag": false}, {"@_fa": "true", "prism:url": "https://api.elsevier.com/content/abstract/scopus_id/0036028154", "dc:identifier": "SCOPUS_ID:0036028154", "dc:title": "Document organization using Kohonen's algorithm", "dc:creator": "Guerrero Bote V.", "prism:publicationName": "Information Processing and Management", "prism:issn": "03064573", "prism:volume": "38", "prism:issueIdentifier": "1", "prism:pageRange": "79-89", "prism:coverDate": "2002-01-01", "prism:doi": "10.1016/S0306-4573(00)00066-2", "citedby-count": "48", "affiliation": [{"@_fa": "true", "affiliation-country": "Spain"}, {"@_fa": "true", "affiliation-country": "Spain"}], "authkeywords": "Browsing | Document clustering | Neural networks | Self-organizing maps | Vectorization", "fund-sponsor": "European Social Fund", "openaccess": "0", "openaccessFlag": false}, {"@_fa": "true", "prism:url": "https://api.elsevier.com/content/abstract/scopus_id/0036028149", "dc:identifier": "SCOPUS_ID:0036028149", "dc:title": "Effective foreign word extraction for Korean information retrieval", "dc:creator": "Kang B.", "prism:publicationName": "Information Processing and Management", "prism:issn": "03064573", "prism:volume": "38", "prism:issueIdentifier": "1", "prism:pageRange": "91-109", "prism:coverDate": "2002-01-01", "prism:doi": "10.1016/S0306-4573(00)00065-0", "citedby-count": "9", "affiliation": [{"@_fa": "true", "affiliation-country": "South Korea"}], "authkeywords": "Foreign word recognition | Information retrieval | Word segmentation", "fund-sponsor": "Korea Science and Engineering Foundation", "openaccess": "0", "openaccessFlag": false}, {"@_fa": "true", "prism:url": "https://api.elsevier.com/content/abstract/scopus_id/0036028148", "dc:identifier": "SCOPUS_ID:0036028148", "dc:title": "Discovering authorities and hubs in different topological web graph structures", "dc:creator": "Meghabghab G.", "prism:publicationName": "Information Processing and Management", "prism:issn": "03064573", "prism:volume": "38", "prism:issueIdentifier": "1", "prism:pageRange": "111-140", "prism:coverDate": "2002-01-01", "prism:doi": "10.1016/S0306-4573(01)00019-X", "citedby-count": "14", "authkeywords": "Authority web page | Bipartite graphs | Citation analysis | Complete bipartite graphs | General graphs | Graph theory | Hub web page | In-degree graphs | Linear algebra | Out-degree graphs | Principal eigenvalue | Principal eigenvector | Web algorithms | Web graph | Web page as a hub web page and an authority web page", "openaccess": "0", "openaccessFlag": false}, {"@_fa": "true", "prism:url": "https://api.elsevier.com/content/abstract/scopus_id/0036028146", "dc:identifier": "SCOPUS_ID:0036028146", "dc:title": "Improving the retrieval effectiveness of very short queries", "dc:creator": "Crouch C.", "prism:publicationName": "Information Processing and Management", "prism:issn": "03064573", "prism:volume": "38", "prism:issueIdentifier": "1", "prism:pageRange": "1-36", "prism:coverDate": "2002-01-01", "prism:doi": "10.1016/S0306-4573(01)00023-1", "citedby-count": "24", "affiliation": [{"@_fa": "true", "affiliation-country": "United States"}, {"@_fa": "true", "affiliation-country": "United States"}], "authkeywords": "Pseudo-feedback | Query drift | Reranking | TREC | Very short queries", "openaccess": "0", "openaccessFlag": false}]}}